Workbook

Sheet Data
A1: Month | B1: Statement Tupe | C1: Office Code | D1: Operating Office | E1: Unique Ref No | F1: Policy Number | G1: Endorsement Number | H1: Policy Holder Name | I1: Effective Start Date | J1: Policy Expiry Date | K1: Product Code | L1: Lob Description | M1: Premium | N1: Brock % | O1: Commission | P1: PIBL | Q1: CN | R1: Inst | S1: Name for Updation | T1: HOD | U1: CSC | V1: Invoice No | W1: Bill ID | X1: Allocated Person | Y1: RFQ status(Yes/No) | Z1: RFQ No | AA1: Modification remarks | AB1: Remarks | AC1: Sachin | AD1: reason
A2: Jun'25 | C2: 272300 | D2: DO 21 NEW DELHI | E2: OIC/25-26/927 | F2: 272300/11/2024/109 | G2: 0 | H2: PARIVAR SEVA SANSTHA | I2: 45108 | J2: 45473 | K2: FIR-PRD-010 | L2: ORIENTAL BHARAT SOOKSHMA UDYAM SURAKSHA POLICY | M2: 59999 | N2: 20.047001 | O2: 12028 | P2: Delhi | Q2: 441579 | R2: 0 | T2: Hemant Kumar Gupta | U2: Sasank S | V2: GGN/23-24/383 | W2: 3080 | X2: Rushiraj | AB2: Excess | AC2: Updation done in Saiba | AD2: Jun'23
A3: Jun'25 | C3: 510000 | D3: CBRO DELHI | E3: OIC/25-26/928 | F3: 510000/48/2023/1560 | G3: 4 | H3: DENTSU WEBCHUTNEY PRIVATE LIMITED | I3: 44964 | J3: 45291 | K3: MIST-PRD-890 | L3: GROUP MEDICLAIM -TAILORMADE-RISK FLOATER | M3: 15137 | N3: 5 | O3: 756.85 | P3: Delhi | Q3: 430685 | R3: NE | T3: Amit Pandey | U3: Niladri Mangal Choudhury | V3: GGN/23-24/384 | W3: 3081 | X3: Rushiraj | AC3: NE | AD3: Jun'23
A4: Jun'25 | C4: 540000 | D4: CBO BANGALORE | E4: OIC/25-26/929 | F4: 421300/48/2023/1166 | G4: 5 | H4: ATRIA CONVERGENCE TECHNOLOGIES LIMITED | I4: 44896 | J4: 45260 | K4: MIST-PRD-890 | L4: GROUP MEDICLAIM -TAILORMADE-RISK FLOATER | M4: -6720 | N4: 7.5 | O4: -504 | P4: Bangalore | Q4: 414344 | R4: E5 | T4: Jayachitra M | U4: Vinod Kumar Heggadadevanapura Thammaiah | V4: BLR/23-24/183 | W4: 3123 | X4: Rushiraj | AC4: Updation done in Saiba | AD4: Jun'23
A5: Jun'25 | C5: 510000 | D5: CBRO DELHI | E5: OIC/25-26/930 | F5: 510000/48/2023/1556 | G5: 4 | H5: DENTSU AEGIS NETWORK INDIA PRIVATE LIMITED | I5: 44938 | J5: 45291 | K5: MIST-PRD-890 | L5: GROUP MEDICLAIM -TAILORMADE-RISK FLOATER | M5: 36689 | N5: 5 | O5: 1834.45 | P5: Delhi | Q5: 430587 | R5: NE | T5: Amit Pandey | U5: Niladri Mangal Choudhury | V5: GGN/23-24/384 | W5: 3081 | X5: Rushiraj | AC5: NE | AD5: Jun'23
A6: Jun'25 | C6: 222105 | D6: KANPUR DEHAT | E6: OIC/25-26/931 | F6: 222105/48/2024/580 | G6: 0 | H6: SACHIN MALIK, | I6: 45098 | J6: 45463 | K6: MIST-PRD-943 | L6: HAPPY FAMILY FLOATER POLICY-2021 | M6: 24849 | N6: 14.998591 | O6: 3000 | P6: Delhi | Q6: 441057 | R6: 0 | T6: Kushal Bhatia | U6: Navneet Arora | V6: GGN/23-24/381 | W6: 3078 | X6: Rushiraj | AC6: Updation done in Saiba | AD6: Jun'23
A7: Jun'25 | C7: 540000 | D7: CBO BANGALORE | E7: OIC/25-26/932 | F7: 421300/48/2023/1048 | G7: 7 | H7: WAFER SPACE SEMICONDUCTOR TECHNOLOGIES PVT LTD | I7: 44812 | J7: 45176 | K7: MIST-PRD-890 | L7: GROUP MEDICLAIM -TAILORMADE-RISK FLOATER | M7: 10358 | N7: 7.5 | O7: 776.85 | P7: Bangalore | Q7: 404320 | R7: NE | T7: Jaya Chitra.M | U7: Deep Shikha | V7: BLR/23-24/183 | W7: 3123 | X7: Rushiraj | AC7: NE | AD7: Jun'23
A8: Jun'25 | C8: 510000 | D8: CBRO DELHI | E8: OIC/25-26/933 | F8: 510000/11/2024/117 | G8: 0 | H8: JCB INDIA LIMITED | I8: 45078 | J8: 45443 | K8: FIR-PRD-009 | L8: ORIENTAL BHARAT LAGHU UDYAM SURAKSHA POLICY | M8: 893665 | N8: 15.352397 | O8: 137199 | P8: Delhi | Q8: NE | R8: NE | T8: Darvesh Panchal | U8: Rohit Kumar Mehndiratta | V8: GGN/23-24/384 | W8: 3081 | X8: Rushiraj | Y8: 215079 | Z8: Yes | AC8: RFQ | AD8: Jun'23
A9: Jun'25 | C9: 132000 | D9: DO JOGESHWARI | E9: OIC/25-26/934 | F9: 132000/11/2022/413 | G9: 3 | H9: Allied Blender & Distillers Pvt Ltd | I9: 44441 | J9: 44805 | K9: FIR-PRD-009 | L9: ORIENTAL BHARAT LAGHU UDYAM SURAKSHA POLICY | M9: -45897 | N9: 10.813343 | O9: -4963 | P9: Mumbai | Q9: 360481 | R9: NE | T9: Susmeet Kaur | U9: Pooja Yadav | V9: MUM/C/23-24/41 | W9: 3100 | X9: Rushiraj | AC9: NE | AD9: Jun'23
A10: Jun'25 | C10: 212203 | D10: CBO 13 N-34 C.PLACE | E10: OIC/25-26/935 | F10: 212203/31/2024/619 | G10: 0 | H10: NHPC LIMITED | I10: 45093 | J10: 45458 | K10: MOT-PRD-015 | L10: STANDALONE OWN DAMAGE(OD)-PRIVATE CAR | M10: 8935 | N10: 14.997202 | O10: 1340 | P10: Delhi | Q10: 443967 | R10: 0 | T10: Saurabh Dwivedi | U10: Mohit Mendiratta | V10: GGN/23-24/378 | W10: 3075 | X10: Rushiraj | AC10: Updation done in Saiba | AD10: Jun'23
A11: Jun'25 | C11: 212200 | D11: NEW DELHI DO 10 | E11: OIC/25-26/936 | F11: 212200/48/2024/267 | G11: 0 | H11: EXCEL PACK PVT LTD | I11: 45090 | J11: 45455 | K11: MIST-PRD-753 | L11: BURGLARY FLOATER | M11: 270 | N11: 12.592593 | O11: 34 | P11: Delhi | Q11: NE | R11: NE | T11: Aradhana Dwivedi | U11: Amit Wali | V11: GGN/23-24/377 | W11: 3074 | X11: Rushiraj | Z11: No | AC11: NE | AD11: Jun'23
A12: Jun'25 | C12: 510000 | D12: CBRO DELHI | E12: OIC/25-26/937 | F12: 510000/48/2023/1556 | G12: 3 | H12: DENTSU AEGIS NETWORK INDIA PRIVATE LIMITED | I12: 44938 | J12: 45291 | K12: MIST-PRD-890 | L12: GROUP MEDICLAIM -TAILORMADE-RISK FLOATER | M12: 63472 | N12: 5 | O12: 3173.6 | P12: Delhi | Q12: 430587 | R12: NE | T12: Amit Pandey | U12: Niladri Mangal Choudhury | V12: GGN/23-24/384 | W12: 3081 | X12: Rushiraj | AC12: NE | AD12: Jun'23
A13: Jun'25 | C13: 163600 | D13: DO IV PUNE | E13: OIC/25-26/938 | F13: 163600/21/2024/3/0001 | G13: 0 | H13: RATHI DYE CHEM (P) LTD | I13: 45078 | J13: 45443 | K13: MC-PRD-015 | L13: MARINE CARGO - OPEN COVER | M13: 9789 | N13: 20.002043 | O13: 1958 | P13: Pune | Q13: NE | R13: NE | T13: Smita Lokapure | U13: Vishal Sushil Pachisia | V13: PUN/23-24/49 | W13: 3090 | X13: Rushiraj | Z13: No | AC13: NE | AD13: Jun'23
A14: Jun'25 | C14: 215600 | D14: DO 4 NEW DELHI | E14: OIC/25-26/946 | F14: 215600/48/2023/1883 | G14: 12 | H14: HCL INFOSYSTEMS LTD | I14: 44835 | J14: 45199 | K14: MIST-PRD-890 | L14: GROUP MEDICLAIM -TAILORMADE-RISK FLOATER | M14: 1154835 | N14: 7.6434296 | O14: 88269 | P14: Delhi | Q14: 405703 | R14: M3 | T14: Abhishek Sharma | U14: Ishita Sharma | V14: GGN/23-24/379 | W14: 3076 | X14: Rushiraj | AC14: NE | AD14: Jun'23
A15: Jun'25 | C15: 510000 | D15: CBRO DELHI | E15: OIC/25-26/939 | F15: 510000/31/2024/47 | G15: 0 | H15: JCB INDIA LIMITED | I15: 45105 | J15: 45470 | K15: MOT-PRD-006 | L15: MISCELANEOUS CLASS D VEHICLES | M15: 10317 | N15: 12.493942 | O15: 1289 | P15: Delhi | Q15: 444639 | R15: 0 | T15: Tejinder Pal Singh | U15: Pushpinder Kaur | V15: GGN/23-24/384 | W15: 3081 | X15: Rushiraj | Z15: No | AC15: Updation Done in Saiba | AD15: Jun'23
A16: Jun'25 | C16: 222105 | D16: KANPUR DEHAT | E16: OIC/25-26/941 | F16: 222105/48/2024/512 | G16: 0 | H16: JAWAID ASHRAF | I16: 45099 | J16: 45464 | K16: MIST-PRD-943 | L16: HAPPY FAMILY FLOATER POLICY-2021 | M16: 84513 | N16: 5.0004141 | O16: 4226 | P16: Delhi | Q16: 440111 | R16: 0 | T16: Kushal Bhatia | U16: Navneet Arora | V16: GGN/23-24/381 | W16: 3078 | X16: Rushiraj | AB16: Part | AC16: Updation done in Saiba | AD16: Jun'23
A17: Jun'25 | C17: 510000 | D17: CBRO DELHI | E17: OIC/25-26/942 | F17: 510000/48/2023/614 | G17: 10 | H17: SUTHERLAND HEALTHCARE SOLUTIONS PRIVATE LIMITED | I17: 44675 | J17: 45039 | K17: MIST-PRD-890 | L17: GROUP MEDICLAIM -TAILORMADE-RISK FLOATER | M17: -1892 | N17: 2.4841438 | O17: -47 | P17: Chennai | Q17: 398821 | R17: NE | T17: Payal Batra | U17: Aas Mohammad | V17: GGN/23-24/384 | W17: 3081 | X17: Rushiraj | AC17: NE | AD17: Jun'23
A18: Jun'25 | C18: 510000 | D18: CBRO DELHI | E18: OIC/25-26/943 | F18: 510000/48/2023/613 | G18: 12 | H18: SUTHERLAND GLOBAL SERVICES PVT LTD | I18: 44675 | J18: 45039 | K18: MIST-PRD-890 | L18: GROUP MEDICLAIM -TAILORMADE-RISK FLOATER | M18: -7456 | N18: 2.4946352 | O18: -186 | P18: Chennai | Q18: 398825 | R18: NE | T18: Payal Batra | U18: Aas Mohammad | V18: GGN/23-24/384 | W18: 3081 | X18: Rushiraj | AC18: NE | AD18: Jun'23
A19: Jun'25 | C19: 212203 | D19: CBO 13 N-34 C.PLACE | E19: OIC/25-26/944 | F19: 212203/31/2024/766 | G19: 0 | H19: EXPORT CREDIT GUARANTEE CORPORATION | I19: 45111 | J19: 45476 | K19: MOT-PRD-015 | L19: STANDALONE OWN DAMAGE(OD)-PRIVATE CAR | M19: 8111 | N19: 14.991986 | O19: 1216 | P19: Delhi | Q19: NE | R19: NE | T19: Suspense | U19: Suspense | V19: GGN/23-24/378 | W19: 3075 | X19: Rushiraj | Z19: No | AC19: NE | AD19: Jun'23
A20: Jun'25 | C20: 421300 | D20: DO 3 BANGALORE | E20: OIC/25-26/945 | F20: 421300/48/2024/482 | G20: 0 | H20: SSP INDIA PRIVATE LIMITED | I20: 45084 | J20: 45449 | K20: MIST-PRD-890 | L20: GROUP MEDICLAIM -TAILORMADE-RISK FLOATER | M20: 2040783 | N20: 7.0000093 | O20: 142855 | P20: Delhi | Q20: 438851 | R20: 0 | T20: Rajiv Choudhary | U20: Ashwini Kumar Srivastava | V20: BLR/23-24/173 | W20: 3066 | X20: Rushiraj | AC20: Updation done in Saiba | AD20: Jun'23
A21: Jun'25 | C21: 111900 | D21: MCDO 14 | E21: OIC/25-26/1295 | F21: 111900/22/2023/895 | G21: 1 | H21: JAYDEEP ASSOCIATES PVT LTD VESSEL: MV SIDDHIVINAYAK II REGNOGMB/NLK/97 YOB: 2023 | I21: 45016 | J21: 45381 | K21: MH-PRD-003 | L21: INLAND VESSELS | M21: 83250 | N21: 11.5003 | O21: 9574 | P21: Mumbai | Q21: 428435 | R21: E1 | T21: Lakshmanan Subramanian Iyer | U21: Saikumar G Shirwatkar | V21: MUM/23-24/568 | W21: 3086 | X21: Rushiraj | AC21: Updation Done in Saiba | AD21: Jun'23
A22: Jun'25 | C22: 510000 | D22: CBRO DELHI | E22: OIC/25-26/947 | F22: 510000/48/2024/423 | G22: 0 | H22: ARTEMIS MEDICARE SERVICES LIMITED | I22: 45090 | J22: 45454 | K22: MIST-PRD-047 | L22: FIDELITY GUARANTEE | M22: 610 | N22: 12.459016 | O22: 76 | P22: Delhi | Q22: 441895 | R22: 0 | T22: Hemant Kumar Gupta | U22: Namit Malhotra | V22: GGN/23-24/384 | W22: 3081 | X22: Rushiraj | AA22: Premium Mismatched | AC22: Modification | AD22: Jun'23
A23: Jun'25 | C23: 111900 | D23: MCDO 14 | E23: OIC/25-26/948 | F23: 111900/22/2024/266 | G23: 0 | H23: 3K MARINE SERVICES | I23: 45104 | J23: 45469 | K23: MH-PRD-003 | L23: INLAND VESSELS | M23: 43125 | N23: 14.998261 | O23: 6468 | P23: Mumbai | Q23: NE | R23: NE | T23: Lakshmanan Subramanian Iyer | U23: Saikumar G Shirwatkar | V23: MUM/23-24/568 | W23: 3086 | X23: Rushiraj | Z23: No | AC23: NE | AD23: Jun'23
A24: Jun'25 | C24: 212203 | D24: CBO 13 N-34 C.PLACE | E24: OIC/25-26/949 | F24: 212203/48/2024/581 | G24: 0 | H24: QRG ENTERPRISES LTD | I24: 45039 | J24: 45382 | K24: MIST-PRD-052 | L24: MONEY INSURANCE | M24: 1178 | N24: 16.468591 | O24: 194 | P24: Delhi | Q24: NE | R24: NE | T24: Vineet Khattar | U24: Sumit Gupta | V24: GGN/23-24/378 | W24: 3075 | X24: Rushiraj | Z24: No | AC24: NE | AD24: Jun'23
A25: Jun'25 | C25: 212203 | D25: CBO 13 N-34 C.PLACE | E25: OIC/25-26/950 | F25: 212203/31/2024/559 | G25: 0 | H25: LESSEE:AC(HQ) SOUTH DELHI M CORP | I25: 45084 | J25: 45449 | K25: MOT-PRD-001 | L25: PRIVATE CAR | M25: 8706 | N25: 13.266713 | O25: 990 | P25: Delhi | Q25: 443804 | R25: 0 | T25: Saurabh Dwivedi | U25: Mohit Mendiratta | V25: GGN/23-24/378 | W25: 3075 | X25: Rushiraj | AA25: TP Brok % need to modify | AC25: Modification | AD25: Jun'23
A26: Jun'25 | C26: 212203 | D26: CBO 13 N-34 C.PLACE | E26: OIC/25-26/951 | F26: 212203/31/2024/687 | G26: 0 | H26: LESSEE POWER GRID CORPORATION OF INDIA LTD | I26: 45097 | J26: 45462 | K26: MOT-PRD-012 | L26: PRIVATE CAR-(3 Years) | M26: 9682 | N26: 14.996901 | O26: 1452 | P26: Delhi | Q26: Contra | R26: Contra | T26: Saurabh Dwivedi | U26: Mohit Mendiratta | V26: GGN/23-24/378 | W26: 3075 | X26: Rushiraj | AC26: Contra | AD26: Jun'23
A27: Jun'25 | C27: 272200 | D27: DO 3 NEW DELHI | E27: OIC/25-26/952 | F27: 272200/31/2024/363 | G27: 0 | H27: JCB INDIA LTD | I27: 45091 | J27: 45456 | K27: MOT-PRD-006 | L27: MISCELANEOUS CLASS D VEHICLES | M27: 12981 | N27: 12.495185 | O27: 1622 | P27: Delhi | Q27: NE | R27: NE | T27: Tejinder Pal Singh | U27: Pushpinder Kaur | V27: GGN/23-24/382 | W27: 3079 | X27: Rushiraj | Z27: No | AC27: NE | AD27: Jun'23
A28: Jun'25 | C28: 212203 | D28: CBO 13 N-34 C.PLACE | E28: OIC/25-26/953 | F28: 212203/31/2024/636 | G28: 0 | H28: MINISTRY OF INFO & BROADCASTING | I28: 45095 | J28: 45460 | K28: MOT-PRD-001 | L28: PRIVATE CAR | M28: 9224 | N28: 13.356461 | O28: 1232 | P28: Delhi | Q28: 443826 | R28: 0 | T28: Saurabh Dwivedi | U28: Mohit Mendiratta | V28: GGN/23-24/378 | W28: 3075 | X28: Rushiraj | AA28: TP Brok % need to modify | AC28: Modification | AD28: Jun'23
A29: Jun'25 | C29: 212203 | D29: CBO 13 N-34 C.PLACE | E29: OIC/25-26/954 | F29: 212203/31/2024/596 | G29: 0 | H29: EAST DELHI MUNICIPAL CORPORATION | I29: 45088 | J29: 45453 | K29: MOT-PRD-001 | L29: PRIVATE CAR | M29: 8512 | N29: 13.228383 | O29: 1126 | P29: Delhi | Q29: 443822 | R29: 0 | T29: Saurabh Dwivedi | U29: Mohit Mendiratta | V29: GGN/23-24/378 | W29: 3075 | X29: Rushiraj | AA29: TP Brok % need to modify | AC29: Modification | AD29: Jun'23
A30: Jun'25 | C30: 212203 | D30: CBO 13 N-34 C.PLACE | E30: OIC/25-26/955 | F30: 212203/31/2024/662 | G30: 0 | H30: DIRECTORATE OF TRANSPORT | I30: 45099 | J30: 45464 | K30: MOT-PRD-001 | L30: PRIVATE CAR | M30: 8522 | N30: 13.224595 | O30: 1127 | P30: Delhi | Q30: 443832 | R30: 0 | T30: Saurabh Dwivedi | U30: Mohit Mendiratta | V30: GGN/23-24/378 | W30: 3075 | X30: Rushiraj | AA30: TP Brok % need to modify | AC30: Modification | AD30: Jun'23
A31: Jun'25 | C31: 215600 | D31: DO 4 NEW DELHI | E31: OIC/25-26/956 | F31: 215600/48/2024/666 | G31: 0 | H31: Lumax Ancillary Ltd | I31: 45017 | J31: 45382 | K31: MIST-PRD-061 | L31: All RISK | M31: 626 | N31: 12.460064 | O31: 78 | P31: Delhi | Q31: 430568 | R31: 0 | T31: Rohit Kumar Mendiratta | U31: Prince Tayal | V31: GGN/23-24/379 | W31: 3076 | X31: Rushiraj | AC31: Updation done in Saiba | AD31: Jun'23
A32: Jun'25 | C32: 212203 | D32: CBO 13 N-34 C.PLACE | E32: OIC/25-26/957 | F32: 212203/31/2024/556 | G32: 0 | H32: LESSEE:AC(HQ) SOUTH DELHI M CORP | I32: 45084 | J32: 45449 | K32: MOT-PRD-001 | L32: PRIVATE CAR | M32: 3358 | N32: 10.48243 | O32: 352 | P32: Delhi | Q32: 443801 | R32: 0 | T32: Saurabh Dwivedi | U32: Mohit Mendiratta | V32: GGN/23-24/378 | W32: 3075 | X32: Rushiraj | AA32: TP Brok % need to modify | AC32: Modification | AD32: Jun'23
A33: Jun'25 | C33: 510000 | D33: CBRO DELHI | E33: OIC/25-26/958 | F33: 510000/48/2023/765 | G33: 6 | H33: Sutherland Global Services Private Limited | I33: 44713 | J33: 45077 | K33: MIST-PRD-890 | L33: GROUP MEDICLAIM -TAILORMADE-RISK FLOATER | M33: -1036 | N33: 3 | O33: -31.08 | P33: Chennai | Q33: 418715 | R33: NE | T33: Payal Batra | U33: Aas Mohammad | V33: GGN/23-24/384 | W33: 3081 | X33: Rushiraj | AC33: NE | AD33: Jun'23
A34: Jun'25 | C34: 411700 | D34: DO 7 CHENNAI | E34: OIC/25-26/959 | F34: 411700/48/2023/2426 | G34: 8 | H34: FINANCIAL SOFTWARE & SYSTEMS (P) LTD | I34: 44835 | J34: 45199 | K34: MIST-PRD-890 | L34: GROUP MEDICLAIM -TAILORMADE-RISK FLOATER | M34: 4579 | N34: 1 | O34: 45.79 | P34: Chennai | Q34: 408012 | R34: E7 | T34: Meenakshi Menon | U34: Sudha.S | V34: CHN/23-24/123 | W34: 3069 | X34: Rushiraj | AC34: Saiba Error | AD34: Jun'23
A35: Jun'25 | C35: 510000 | D35: CBRO DELHI | E35: OIC/25-26/960 | F35: 510000/48/2023/392 | G35: 12 | H35: NORTHERN MARINE MANAGEMENT (INDIA) PVTLTD | I35: 44681 | J35: 45045 | K35: MIST-PRD-890 | L35: GROUP MEDICLAIM -TAILORMADE-RISK FLOATER | M35: 1330 | N35: 5 | O35: 66.5 | P35: Mumbai | Q35: 382317 | R35: E11 | T35: Ashita Lotia | U35: Arpita R Kochrekar | V35: GGN/23-24/384 | W35: 3081 | X35: Rushiraj | AC35: Updation done in Saiba | AD35: Jun'23
A36: Jun'25 | C36: 510000 | D36: CBRO DELHI | E36: OIC/25-26/961 | F36: 510000/48/2023/1559 | G36: 3 | H36: DENTSU NETWORK ADVERTISING PRIVATE LIMITED | I36: 44964 | J36: 45291 | K36: MIST-PRD-890 | L36: GROUP MEDICLAIM -TAILORMADE-RISK FLOATER | M36: -31233 | N36: 5 | O36: -1561.65 | P36: Delhi | Q36: 430593 | R36: NE | T36: Amit Pandey | U36: Niladri Mangal Choudhury | V36: GGN/23-24/384 | W36: 3081 | X36: Rushiraj | AC36: NE | AD36: Jun'23
A37: Jun'25 | C37: 510000 | D37: CBRO DELHI | E37: OIC/25-26/962 | F37: 510000/48/2024/417 | G37: 0 | H37: ARTEMIS MEDICARE SERVICES LIMITED | I37: 45090 | J37: 45454 | K37: MIST-PRD-025 | L37: PLATE GLASS INSURANCE | M37: 625 | N37: 12.48 | O37: 78 | P37: Delhi | Q37: 441894 | R37: 0 | T37: Hemant Kumar Gupta | U37: Namit Malhotra | V37: GGN/23-24/384 | W37: 3081 | X37: Rushiraj | AB37: Excess | AC37: Updation done in Saiba | AD37: Jun'23
A38: Jun'25 | C38: 510000 | D38: CBRO DELHI | E38: OIC/25-26/963 | F38: 510000/48/2023/1559 | G38: 4 | H38: DENTSU NETWORK ADVERTISING PRIVATE LIMITED | I38: 44964 | J38: 45291 | K38: MIST-PRD-890 | L38: GROUP MEDICLAIM -TAILORMADE-RISK FLOATER | M38: -16143 | N38: 5 | O38: -807.15 | P38: Delhi | Q38: 430593 | R38: NE | T38: Amit Pandey | U38: Niladri Mangal Choudhury | V38: GGN/23-24/384 | W38: 3081 | X38: Rushiraj | AC38: NE | AD38: Jun'23
A39: Jun'25 | C39: 510000 | D39: CBRO DELHI | E39: OIC/25-26/964 | F39: 510000/31/2024/41 | G39: 0 | H39: JCB INDIA LTD | I39: 45093 | J39: 45458 | K39: MOT-PRD-006 | L39: MISCELANEOUS CLASS D VEHICLES | M39: 13058 | N39: 12.498085 | O39: 1632 | P39: Pune | Q39: NE | R39: NE | T39: Azmi Raza | U39: Salman Shaikh | V39: GGN/23-24/384 | W39: 3081 | X39: Rushiraj | Z39: No | AC39: NE | AD39: Jun'23
A40: Jun'25 | C40: 212203 | D40: CBO 13 N-34 C.PLACE | E40: OIC/25-26/965 | F40: 212203/31/2024/530 | G40: 0 | H40: EAST DELHI MUNICIPAL CORPORATION | I40: 45081 | J40: 45446 | K40: MOT-PRD-001 | L40: PRIVATE CAR | M40: 8512 | N40: 0 | O40: 0 | P40: Delhi | Q40: 443787 | R40: 0 | T40: Saurabh Dwivedi | U40: Mohit Mendiratta | V40: GGN/23-24/378 | W40: 3075 | X40: Rushiraj | AB40: Part | AC40: Updation done in Saiba | AD40: Jun'23
A41: Jun'25 | C41: 212203 | D41: CBO 13 N-34 C.PLACE | E41: OIC/25-26/966 | F41: 212203/31/2024/533 | G41: 0 | H41: PRASAR BHARTI DOORDARSHAN KENDRA | I41: 45082 | J41: 45447 | K41: MOT-PRD-001 | L41: PRIVATE CAR | M41: 8663 | N41: 0 | O41: 0 | P41: Delhi | Q41: 443790 | R41: 0 | T41: Saurabh Dwivedi | U41: Mohit Mendiratta | V41: GGN/23-24/378 | W41: 3075 | X41: Rushiraj | AB41: Part | AC41: Updation done in Saiba | AD41: Jun'23
A42: Jun'25 | C42: 132500 | D42: DO - 7 | E42: OIC/25-26/967 | F42: 132500/48/2024/25 | G42: 0 | H42: RAKESH S GUPTA | I42: 45084 | J42: 45449 | K42: MIST-PRD-003 | L42: PA INDIVIDUAL | M42: 11275 | N42: 16.505543 | O42: 1861 | P42: Mumbai | Q42: 442036 | R42: 0 | T42: Kushal Bhatia | U42: Anju Shukla | V42: Invoice in process | W42: Invoice in process | X42: Rushiraj | AB42: Excess | AC42: Invoice in Process | AD42: Jun'23
A43: Jun'25 | C43: 222105 | D43: KANPUR DEHAT | E43: OIC/25-26/968 | F43: 222105/48/2024/639 | G43: 0 | H43: RAJEEV SNAIR | I43: 45116 | J43: 45481 | K43: MIST-PRD-943 | L43: HAPPY FAMILY FLOATER POLICY-2021 | M43: 33053 | N43: 5.0010589 | O43: 1653 | P43: Mumbai | Q43: 441476 | R43: 0 | T43: Kushal Bhatia | U43: Anju Shukla | V43: GGN/23-24/381 | W43: 3078 | X43: Rushiraj | AB43: Part | AC43: Updation done in Saiba | AD43: Jun'23
A44: Jun'25 | C44: 212203 | D44: CBO 13 N-34 C.PLACE | E44: OIC/25-26/969 | F44: 212203/31/2024/672 | G44: 0 | H44: THE DIRECTOR ANERT | I44: 45101 | J44: 45466 | K44: MOT-PRD-015 | L44: STANDALONE OWN DAMAGE(OD)-PRIVATE CAR | M44: 12728 | N44: 15.006285 | O44: 1910 | P44: Delhi | Q44: 443971 | R44: 0 | T44: Saurabh Dwivedi | U44: Mohit Mendiratta | V44: GGN/23-24/378 | W44: 3075 | X44: Rushiraj | AC44: Updation done in Saiba | AD44: Jun'23
A45: Jun'25 | C45: 215600 | D45: DO 4 NEW DELHI | E45: OIC/25-26/970 | F45: 215600/48/2023/1883 | G45: 11 | H45: HCL INFOSYSTEMS LTD | I45: 44835 | J45: 45199 | K45: MIST-PRD-890 | L45: GROUP MEDICLAIM -TAILORMADE-RISK FLOATER | M45: -211 | N45: 7.5829384 | O45: -16 | P45: Delhi | Q45: 405703 | R45: NE | T45: Abhishek Sharma | U45: Ishita Sharma | V45: GGN/23-24/379 | W45: 3076 | X45: Rushiraj | AC45: NE | AD45: Jun'23
A46: Jun'25 | C46: 510000 | D46: CBRO DELHI | E46: OIC/25-26/971 | F46: 510000/48/2023/872 | G46: 12 | H46: JCB INDUSTRIES PRIVATE LIMITED | I46: 44803 | J46: 45077 | K46: MIST-PRD-890 | L46: GROUP MEDICLAIM -TAILORMADE-RISK FLOATER | M46: 18827 | N46: 0 | O46: 0 | P46: Delhi | Q46: 387302 | R46: NE | T46: Sonia Schofield | U46: Vikas Saxena | V46: GGN/23-24/384 | W46: 3081 | X46: Rushiraj | AC46: NE | AD46: Jun'23
A47: Jun'25 | C47: 222105 | D47: KANPUR DEHAT | E47: OIC/25-26/972 | F47: 222105/48/2024/653 | G47: 0 | H47: JITENDER SHARMA | I47: 45108 | J47: 45473 | K47: MIST-PRD-943 | L47: HAPPY FAMILY FLOATER POLICY-2021 | M47: 46462 | N47: 4.9997848 | O47: 2323 | P47: Delhi | Q47: NE | R47: NE | T47: Kushal Bhatia | U47: Ankit Kumar Gangwar | V47: GGN/23-24/381 | W47: 3078 | X47: Rushiraj | Z47: No | AC47: NE | AD47: Jun'23
A48: Jun'25 | C48: 212203 | D48: CBO 13 N-34 C.PLACE | E48: OIC/25-26/973 | F48: 212203/31/2024/629 | G48: 1 | H48: GURUGRAM METROPOLITAN DEVELOPMENT A | I48: 45116 | J48: 45116 | K48: MOT-PRD-001 | L48: PRIVATE CAR | M48: -12919 | N48: 13.824599 | O48: -1786 | P48: Delhi | Q48: NE | R48: NE | T48: Suspense | U48: Suspense | V48: GGN/23-24/378 | W48: 3075 | X48: Rushiraj | AC48: NE | AD48: Jun'23
A49: Jun'25 | C49: 163600 | D49: DO IV PUNE | E49: OIC/25-26/974 | F49: 163600/21/2024/8 | G49: 0 | H49: RATHI DYE CHEM (P) LTD | I49: 45103 | K49: MC-PRD-001 | L49: MARINE CARGO - SINGLE VOYAGE (INLAND TRANSIT) POLICY | M49: 5848 | N49: 20.00684 | O49: 1170 | P49: Pune | Q49: NE | R49: NE | T49: Smita Lokapure | U49: Vishal Sushil Pachisia | V49: PUN/23-24/49 | W49: 3090 | X49: Rushiraj | Z49: No | AC49: NE | AD49: Jun'23
A50: Jun'25 | C50: 161800 | D50: DO CHINCHWAD | E50: OIC/25-26/975 | F50: 161800/48/2023/1961 | G50: 7 | H50: GKN SINTER METALS PRIVATE LIMITED | I50: 44838 | J50: 45202 | K50: MIST-PRD-890 | L50: GROUP MEDICLAIM -TAILORMADE-RISK FLOATER | M50: -92241 | N50: 7.5000054 | O50: -6918.08 | P50: Pune | Q50: 403493 | R50: NE | T50: Amarjeet Sahu | U50: Shahaji Dhage | V50: PUN/C/23-24/03 | W50: 3101 | X50: Rushiraj | AC50: NE | AD50: Jun'23
A51: Jun'25 | C51: 161800 | D51: DO CHINCHWAD | E51: OIC/25-26/976 | F51: 161800/48/2023/1961 | G51: 6 | H51: GKN SINTER METALS PRIVATE LIMITED | I51: 44838 | J51: 45202 | K51: MIST-PRD-890 | L51: GROUP MEDICLAIM -TAILORMADE-RISK FLOATER | M51: 58872 | N51: 7.5 | O51: 4415.4 | P51: Pune | Q51: 403493 | R51: NE | T51: Amarjeet Sahu | U51: Shahaji Dhage | V51: PUN/C/23-24/03 | W51: 3101 | X51: Rushiraj | AC51: NE | AD51: Jun'23
A52: Jun'25 | C52: 272200 | D52: DO 3 NEW DELHI | E52: OIC/25-26/977 | F52: 272200/48/2024/809 | G52: 0 | H52: SUNITA SINGH | I52: 45101 | J52: 45466 | K52: MIST-PRD-943 | L52: HAPPY FAMILY FLOATER POLICY-2021 | M52: 16055 | N52: 14.998443 | O52: 2408 | P52: Delhi | Q52: 442896 | R52: 0 | T52: Kushal Bhatia | U52: Navneet Arora | V52: GGN/23-24/382 | W52: 3079 | X52: Rushiraj | AC52: Updation done in Saiba | AD52: Jun'23
A53: Jun'25 | C53: 272200 | D53: DO 3 NEW DELHI | E53: OIC/25-26/978 | F53: 272200/31/2024/437 | G53: 0 | H53: HINDUSTAN ZINC LTD | I53: 45107 | J53: 45472 | K53: MOT-PRD-006 | L53: MISCELANEOUS CLASS D VEHICLES | M53: 13492 | N53: 12.496294 | O53: 1686 | P53: Ludhiana | Q53: 442913 | R53: 0 | T53: Anil Patil | U53: Manisha Kirdkude | V53: GGN/23-24/382 | W53: 3079 | X53: Rushiraj | AB53: Excess | AC53: Updation done in Saiba | AD53: Jun'23
A54: Jun'25 | C54: 540000 | D54: CBO BANGALORE | E54: OIC/25-26/980 | F54: 421300/48/2023/1048 | G54: 6 | H54: WAFER SPACE SEMICONDUCTOR TECHNOLOGIES PVT LTD | I54: 44812 | J54: 45176 | K54: MIST-PRD-890 | L54: GROUP MEDICLAIM -TAILORMADE-RISK FLOATER | M54: 22043 | N54: 7.5000227 | O54: 1653.23 | P54: Bangalore | Q54: 404320 | R54: NE | T54: Jaya Chitra.M | U54: Deep Shikha | V54: BLR/23-24/183 | W54: 3123 | X54: Rushiraj | AC54: NE | AD54: Jun'23
A55: Jun'25 | C55: 212203 | D55: CBO 13 N-34 C.PLACE | E55: OIC/25-26/981 | F55: 212203/31/2024/687 | G55: 1 | H55: LESSEE POWER GRID CORPORATION OF INDIA LTD | I55: 45097 | J55: 45097 | K55: MOT-PRD-012 | L55: PRIVATE CAR-(3 Years) | M55: -9682 | N55: 14.996901 | O55: -1452 | P55: Delhi | Q55: Contra | R55: Contra | T55: Saurabh Dwivedi | U55: Mohit Mendiratta | V55: GGN/23-24/378 | W55: 3075 | X55: Rushiraj | AC55: Contra | AD55: Jun'23
A56: Jun'25 | C56: 414890 | D56: BC SINGAPERUMAL KOIL | E56: OIC/25-26/982 | F56: 414890/31/2024/603 | G56: 0 | H56: JOYSON ANAND ABHISHEK SAFETY SYSTEMS PVT LTD | I56: 45101 | J56: 45466 | K56: MOT-PRD-006 | L56: MISCELANEOUS CLASS D VEHICLES | M56: 9876 | N56: 12.494937 | O56: 1234 | P56: Chennai | Q56: 439844 | R56: 0 | T56: Meiyappan M | U56: Raghunathan S | V56: CHN/23-24/125 | W56: 3071 | X56: Rushiraj | AB56: Excess | AC56: Updation done in Saiba | AD56: Jun'23
A57: Jun'25 | C57: 510000 | D57: CBRO DELHI | E57: OIC/25-26/983 | F57: 510000/11/2024/122 | G57: 0 | H57: ARTEMIS MEDICARE SERVICES LIMITED | I57: 45089 | J57: 45454 | K57: FIR-PRD-006 | L57: STANDARD FIRE -- New Tariff | M57: 3936183 | N57: 13.890741 | O57: 546765 | P57: Delhi | Q57: 441887 | R57: 0 | T57: Hemant Kumar Gupta | U57: Namit Malhotra | V57: GGN/23-24/384 | W57: 3081 | X57: Rushiraj | AB57: Excess | AC57: Updation done in Saiba | AD57: Jun'23
A58: Jun'25 | C58: 132000 | D58: DO JOGESHWARI | E58: OIC/25-26/984 | F58: 132000/11/2022/408 | G58: 4 | H58: Allied Blender & Distillers Pvt Ltd | I58: 44441 | J58: 44805 | K58: FIR-PRD-009 | L58: ORIENTAL BHARAT LAGHU UDYAM SURAKSHA POLICY | M58: -81873 | N58: 10.446667 | O58: -8553 | P58: Mumbai | Q58: 360471 | R58: NE | T58: Susmeet Kaur | U58: Pooja Yadav | V58: MUM/C/23-24/41 | W58: 3100 | X58: Rushiraj | AC58: NE | AD58: Jun'23
A59: Jun'25 | C59: 222105 | D59: KANPUR DEHAT | E59: OIC/25-26/985 | F59: 222105/48/2024/616 | G59: 0 | H59: SANNE GANGADHAR | I59: 45103 | J59: 45468 | K59: MIST-PRD-943 | L59: HAPPY FAMILY FLOATER POLICY-2021 | M59: 32126 | N59: 15.000311 | O59: 4819 | P59: Delhi | Q59: 442901 | R59: 0 | T59: Kushal Bhatia | U59: Navneet Arora | V59: GGN/23-24/381 | W59: 3078 | X59: Rushiraj | AC59: Updation done in Saiba | AD59: Jun'23
A60: Jun'25 | C60: 441202 | D60: BO NEYYATINKARA | E60: OIC/25-26/986 | F60: 441202/48/2023/727 | G60: 15 | H60: TECHVERSANT INFOTECH PRIVATE LIMITED | I60: 44851 | J60: 45215 | K60: MIST-PRD-890 | L60: GROUP MEDICLAIM -TAILORMADE-RISK FLOATER | M60: 52 | N60: 5.7692308 | O60: 3 | P60: Chennai | Q60: 405682 | R60: NE | T60: Balakrishnan M | U60: Balakrishnan.G | V60: CHN/23-24/126 | W60: 3072 | X60: Rushiraj | AC60: NE | AD60: Jun'23
A61: Jun'25 | C61: 540000 | D61: CBO BANGALORE | E61: OIC/25-26/987 | F61: 421300/48/2023/753 | G61: 8 | H61: AUMA INDIA PRIVATE LIMITED | I61: 44783 | J61: 45147 | K61: MIST-PRD-890 | L61: GROUP MEDICLAIM -TAILORMADE-RISK FLOATER | M61: 36030 | N61: 7 | O61: 2522.1 | P61: Bangalore | Q61: 423936 | R61: E3 | T61: Arun Kumar G.E. | U61: Karthik Rajappa | V61: BLR/23-24/183 | W61: 3123 | X61: Rushiraj | AB61: Part | AC61: Updation done in Saiba | AD61: Jun'23
A62: Jun'25 | C62: 215600 | D62: DO 4 NEW DELHI | E62: OIC/25-26/988 | F62: 215600/48/2024/664 | G62: 0 | H62: Lumax Ancillary Ltd | I62: 45017 | J62: 45382 | K62: MIST-PRD-061 | L62: All RISK | M62: 2325 | N62: 12.516129 | O62: 291 | P62: Delhi | Q62: 430565 | R62: 0 | T62: Rohit Kumar Mendiratta | U62: Prince Tayal | V62: GGN/23-24/379 | W62: 3076 | X62: Rushiraj | AC62: Updation done in Saiba | AD62: Jun'23
A63: Jun'25 | C63: 212203 | D63: CBO 13 N-34 C.PLACE | E63: OIC/25-26/989 | F63: 212203/31/2024/569 | G63: 0 | H63: LESSEE:AC(HQ) SOUTH DELHI M CORP | I63: 45084 | J63: 45449 | K63: MOT-PRD-001 | L63: PRIVATE CAR | M63: 8706 | N63: 13.266713 | O63: 1155 | P63: Delhi | Q63: 443814 | R63: 0 | T63: Saurabh Dwivedi | U63: Mohit Mendiratta | V63: GGN/23-24/378 | W63: 3075 | X63: Rushiraj | AA63: TP Brok % need to modify | AC63: Modification | AD63: Jun'23
A64: Jun'25 | C64: 212203 | D64: CBO 13 N-34 C.PLACE | E64: OIC/25-26/990 | F64: 212203/31/2024/557 | G64: 0 | H64: LESSEE:AC(HQ) SOUTH DELHI M CORP | I64: 45084 | J64: 45449 | K64: MOT-PRD-001 | L64: PRIVATE CAR | M64: 3690 | N64: 10.894309 | O64: 402 | P64: Delhi | Q64: 443802 | R64: 0 | T64: Saurabh Dwivedi | U64: Mohit Mendiratta | V64: GGN/23-24/378 | W64: 3075 | X64: Rushiraj | AA64: TP Brok % need to modify | AC64: Modification | AD64: Jun'23
A65: Jun'25 | C65: 212203 | D65: CBO 13 N-34 C.PLACE | E65: OIC/25-26/991 | F65: 212203/31/2024/572 | G65: 0 | H65: ENERGY EFFICIENCY SERVICES LIMITED | I65: 45084 | J65: 45449 | K65: MOT-PRD-001 | L65: PRIVATE CAR | M65: 9689 | N65: 13.437919 | O65: 1302 | P65: Delhi | Q65: 443817 | R65: 0 | T65: Saurabh Dwivedi | U65: Mohit Mendiratta | V65: GGN/23-24/378 | W65: 3075 | X65: Rushiraj | AA65: TP Brok % need to modify | AC65: Modification | AD65: Jun'23
A66: Jun'25 | C66: 212203 | D66: CBO 13 N-34 C.PLACE | E66: OIC/25-26/992 | F66: 212203/31/2024/562 | G66: 0 | H66: LESSEE:AC(HQ) SOUTH DELHI M CORP | I66: 45084 | J66: 45449 | K66: MOT-PRD-001 | L66: PRIVATE CAR | M66: 3690 | N66: 10.894309 | O66: 402 | P66: Delhi | Q66: 443807 | R66: 0 | T66: Saurabh Dwivedi | U66: Mohit Mendiratta | V66: GGN/23-24/378 | W66: 3075 | X66: Rushiraj | AA66: TP Brok % need to modify | AC66: Modification | AD66: Jun'23
A67: Jun'25 | C67: 510000 | D67: CBRO DELHI | E67: OIC/25-26/993 | F67: 510000/48/2024/410 | G67: 0 | H67: JCB INDIA LIMITED | I67: 45104 | J67: 45443 | K67: MIST-PRD-751 | L67: BURGLARY | M67: 500 | N67: 12.6 | O67: 63 | P67: Delhi | Q67: 0 | R67: 0 | T67: Darvesh Panchal | U67: Rohit Kumar Mehndiratta | V67: GGN/23-24/384 | W67: 3081 | X67: Rushiraj | Z67: No | AC67: Updation Done in Saiba | AD67: Jun'23
A68: Jun'25 | C68: 222105 | D68: KANPUR DEHAT | E68: OIC/25-26/994 | F68: 222105/48/2024/513 | G68: 0 | H68: MS MAHVISH ASHRAF | I68: 45099 | J68: 45464 | K68: MIST-PRD-094 | L68: ORIENTAL MEDICLAIM INSURANCE POLICY(INDIVIDUAL) | M68: 9352 | N68: 30.004277 | O68: 2806 | P68: Delhi | Q68: 440113 | R68: 0 | T68: Kushal Bhatia | U68: Navneet Arora | V68: GGN/23-24/381 | W68: 3078 | X68: Rushiraj | AB68: Excess | AC68: Updation done in Saiba | AD68: Jun'23
A69: Jun'25 | C69: 212200 | D69: NEW DELHI DO 10 | E69: OIC/25-26/995 | F69: 212200/11/2024/32 | G69: 0 | H69: EXCEL PACK PVT LTD | I69: 45092 | J69: 45457 | K69: FIR-PRD-009 | L69: ORIENTAL BHARAT LAGHU UDYAM SURAKSHA POLICY | M69: 166296 | N69: 17.29747 | O69: 28765 | P69: Delhi | Q69: NE | R69: NE | T69: Aradhana Dwivedi | U69: Amit Wali | V69: GGN/23-24/377 | W69: 3074 | X69: Rushiraj | Z69: No | AC69: NE | AD69: Jun'23
A70: Jun'25 | C70: 510000 | D70: CBRO DELHI | E70: OIC/25-26/996 | F70: 510000/48/2024/51 | G70: 2 | H70: LADY BAMFORD CHARITABLE TRUST | I70: 45034 | J70: 45368 | K70: MIST-PRD-890 | L70: GROUP MEDICLAIM -TAILORMADE-RISK FLOATER | M70: 27762 | N70: 7.5 | O70: 2082.15 | P70: Delhi | Q70: 428430 | R70: NE | T70: Sarfuddin Ansari | U70: Gagan Sharma | V70: GGN/23-24/384 | W70: 3081 | X70: Rushiraj | AC70: NE | AD70: Jun'23
A71: Jun'25 | C71: 510000 | D71: CBRO DELHI | E71: OIC/25-26/997 | F71: 510000/11/2024/121 | G71: 0 | H71: JCB INDIA LTD | I71: 45078 | J71: 45443 | K71: FIR-PRD-003 | L71: INDUSTRIAL ALL RISK POLICY | M71: 16932527 | N71: 16.500006 | O71: 2793868 | P71: Pune | Q71: 441862 | R71: 0 | T71: Darvesh Panchal | U71: Rohit Kumar Mehndiratta | V71: GGN/23-24/384 | W71: 3081 | X71: Rushiraj | AB71: Excess | AC71: Updation done in Saiba | AD71: Jun'23
A72: Jun'25 | C72: 510000 | D72: CBRO DELHI | E72: OIC/25-26/998 | F72: 510000/11/2024/105 | G72: 0 | H72: JCB POWER PRODUCTS INDIA PVT LTD | I72: 45078 | J72: 45443 | K72: FIR-PRD-010 | L72: ORIENTAL BHARAT SOOKSHMA UDYAM SURAKSHA POLICY | M72: 16239 | N72: 15.992364 | O72: 2597 | P72: Delhi | Q72: NE | R72: NE | T72: Darvesh Panchal | U72: Rohit Kumar Mehndiratta | V72: GGN/23-24/384 | W72: 3081 | X72: Rushiraj | Z72: No | AC72: NE | AD72: Jun'23
A73: Jun'25 | C73: 431500 | D73: DO IV HYDERABAD | E73: OIC/25-26/999 | F73: 431500/48/2023/3633 | G73: 5 | H73: WAVEMAKER INDIA PRIVATE LIMITED | I73: 44997 | J73: 45362 | K73: MIST-PRD-001 | L73: GPA - NAMED | M73: -679 | N73: 7.5007364 | O73: -50.93 | P73: Hyderabad | Q73: 424818 | R73: NE | T73: Prasanna Vadhana | U73: Manisha Marda | V73: HYD/23-24/73 | W73: 3082 | X73: Rushiraj | AC73: NE | AD73: Jun'23
A74: Jun'25 | C74: 442600 | D74: DO THODUPUZHA | E74: OIC/25-26/1000 | F74: 442600/11/2024/25 | G74: 0 | H74: Epsilon Carbon Pvt Ltd | I74: 45078 | J74: 45169 | K74: FIR-PRD-012 | L74: ORIENTAL INSURANCE - FLEXI BHARAT LAGHU UDYAM SURAKSHA | M74: 60855 | N74: 21.999836 | O74: 13388 | P74: Mumbai | Q74: NE | R74: NE | T74: Susmeet Kaur | U74: Pooja Yadav | V74: CHN/23-24/127 | W74: 3073 | X74: Rushiraj | Z74: No | AC74: NE | AD74: Jun'23
A75: Jun'25 | C75: 510000 | D75: CBRO DELHI | E75: OIC/25-26/1001 | F75: 510000/48/2023/641 | G75: 13 | H75: SUTHERLAND GLOBAL SERVICES PRIVATE LIMITED | I75: 44750 | J75: 45114 | K75: MIST-PRD-890 | L75: GROUP MEDICLAIM -TAILORMADE-RISK FLOATER | M75: 38082 | N75: 2.4998687 | O75: 952 | P75: Chennai | Q75: 398818 | R75: NE | T75: Payal Batra | U75: Aas Mohammad | V75: GGN/23-24/384 | W75: 3081 | X75: Rushiraj | AC75: NE | AD75: Jun'23
A76: Jun'25 | C76: 421100 | D76: CBU Bangalore | E76: OIC/25-26/1002 | F76: 421100/48/2024/199 | G76: 0 | H76: INFOSTRETCH CORPORATION INDIA PRIVATE LIMITED | I76: 45047 | J76: 45412 | K76: MIST-PRD-890 | L76: GROUP MEDICLAIM -TAILORMADE-RISK FLOATER | M76: 4162162 | N76: 4.9999976 | O76: 208108 | P76: Pune | Q76: 444219 | R76: 0 | T76: Sheetal Gurav | U76: Renny Ignatius Peter | V76: BLR/23-24/172 | W76: 3065 | X76: Rushiraj | Z76: No | AC76: Updation Done in Saiba | AD76: Jun'23
A77: Jun'25 | C77: 510000 | D77: CBRO DELHI | E77: OIC/25-26/1003 | F77: 510000/48/2023/1561 | G77: 3 | H77: DENTSU ADVERTISING AND MEDIA SERVICES INDIA PRIVATE LIMITED | I77: 44938 | J77: 45291 | K77: MIST-PRD-890 | L77: GROUP MEDICLAIM -TAILORMADE-RISK FLOATER | M77: 26665 | N77: 5 | O77: 1333.25 | P77: Delhi | Q77: 430579 | R77: NE | T77: Amit Pandey | U77: Niladri Mangal Choudhury | V77: GGN/23-24/384 | W77: 3081 | X77: Rushiraj | AC77: NE | AD77: Jun'23
A78: Jun'25 | C78: 540000 | D78: CBO BANGALORE | E78: OIC/25-26/1004 | F78: 421300/48/2024/396 | G78: 1 | H78: WAFER SPACE SEMICONDUCTOR TECHNOLOGIES PVT LTD | I78: 45033 | J78: 45398 | K78: MIST-PRD-890 | L78: GROUP MEDICLAIM -TAILORMADE-RISK FLOATER | M78: 1375000 | N78: 7.5 | O78: 103125 | P78: Bangalore | Q78: 441188 | R78: 0 | T78: Jaya Chitra.M | U78: Deep Shikha | V78: BLR/23-24/183 | W78: 3123 | X78: Rushiraj | AC78: Saiba Error | AD78: Jun'23
A79: Jun'25 | C79: 510000 | D79: CBRO DELHI | E79: OIC/25-26/1005 | F79: 510000/48/2023/1609 | G79: 2 | H79: DENTSU WEBCHUTNEY PRIVATE LIMITED | I79: 44960 | J79: 45324 | K79: MIST-PRD-890 | L79: GROUP MEDICLAIM -TAILORMADE-RISK FLOATER | M79: 2422 | N79: 0.5 | O79: 12.11 | P79: Delhi | Q79: 434025 | R79: NE | T79: Amit Pandey | U79: Niladri Mangal Choudhury | V79: GGN/23-24/384 | W79: 3081 | X79: Rushiraj | AC79: NE | AD79: Jun'23
A80: Jun'25 | C80: 540000 | D80: CBO BANGALORE | E80: OIC/25-26/979 | F80: 421300/48/2023/1150 | G80: 4 | H80: ATRIA CONVERGENCE TECHNOLOGIES LIMITED | I80: 44896 | J80: 45260 | K80: MIST-PRD-001 | L80: GPA - NAMED | M80: -161 | N80: 7.4534161 | O80: -12 | P80: Bangalore | Q80: 414345 | R80: E4 | T80: Jayachitra M | U80: Vinod Kumar Heggadadevanapura Thammaiah | V80: BLR/23-24/183 | W80: 3123 | X80: Rushiraj | AC80: Updation Done in Saiba | AD80: Jun'23
A81: Jun'25 | C81: 212203 | D81: CBO 13 N-34 C.PLACE | E81: OIC/25-26/1007 | F81: 212203/31/2024/534 | G81: 0 | H81: PRASAR BHARTI DOORDARSHAN KENDRA | I81: 45082 | J81: 45447 | K81: MOT-PRD-001 | L81: PRIVATE CAR | M81: 8471 | N81: 0 | O81: 0 | P81: Delhi | Q81: 443791 | R81: 0 | T81: Saurabh Dwivedi | U81: Mohit Mendiratta | V81: GGN/23-24/378 | W81: 3075 | X81: Rushiraj | AB81: Part | AC81: Updation done in Saiba | AD81: Jun'23
A82: Jun'25 | C82: 212203 | D82: CBO 13 N-34 C.PLACE | E82: OIC/25-26/1008 | F82: 212203/31/2024/590 | G82: 0 | H82: TRANSLATIONAL H S T I | I82: 45086 | J82: 45451 | K82: MOT-PRD-015 | L82: STANDALONE OWN DAMAGE(OD)-PRIVATE CAR | M82: 8851 | N82: 14.992656 | O82: 1327 | P82: Delhi | Q82: 443959 | R82: 0 | T82: Saurabh Dwivedi | U82: Mohit Mendiratta | V82: GGN/23-24/378 | W82: 3075 | X82: Rushiraj | AC82: Updation done in Saiba | AD82: Jun'23
A83: Jun'25 | C83: 212203 | D83: CBO 13 N-34 C.PLACE | E83: OIC/25-26/1009 | F83: 212203/31/2024/733 | G83: 0 | H83: THE DIRECTOR ANERT | I83: 45105 | J83: 45470 | K83: MOT-PRD-015 | L83: STANDALONE OWN DAMAGE(OD)-PRIVATE CAR | M83: 8871 | N83: 14.992673 | O83: 1330 | P83: Delhi | Q83: 443974 | R83: 0 | T83: Saurabh Dwivedi | U83: Mohit Mendiratta | V83: GGN/23-24/378 | W83: 3075 | X83: Rushiraj | AC83: Updation done in Saiba | AD83: Jun'23
A84: Jun'25 | C84: 132000 | D84: DO JOGESHWARI | E84: OIC/25-26/1010 | F84: 132000/11/2022/409 | G84: 3 | H84: Allied Blender & Distillers Pvt Ltd | I84: 44441 | J84: 44805 | K84: FIR-PRD-009 | L84: ORIENTAL BHARAT LAGHU UDYAM SURAKSHA POLICY | M84: -68208 | N84: 10.105853 | O84: -6893 | P84: Mumbai | Q84: 360468 | R84: NE | T84: Susmeet Kaur | U84: Pooja Yadav | V84: MUM/C/23-24/41 | W84: 3100 | X84: Rushiraj | AC84: NE | AD84: Jun'23
A85: Jun'25 | C85: 510000 | D85: CBRO DELHI | E85: OIC/25-26/1011 | F85: 510000/48/2023/752 | G85: 16 | H85: JCB INDIA LTD | I85: 44713 | J85: 45077 | K85: MIST-PRD-890 | L85: GROUP MEDICLAIM -TAILORMADE-RISK FLOATER | M85: 46903 | N85: 0 | O85: 0 | P85: Pune | Q85: 402796 | R85: NE | T85: Atul Chordiya | U85: Amit Rokade | V85: GGN/23-24/384 | W85: 3081 | X85: Rushiraj | AC85: NE | AD85: Jun'23
A86: Jun'25 | C86: 212203 | D86: CBO 13 N-34 C.PLACE | E86: OIC/25-26/1012 | F86: 212203/31/2024/565 | G86: 0 | H86: LESSEE:AC(HQ) SOUTH DELHI M CORP | I86: 45084 | J86: 45449 | K86: MOT-PRD-001 | L86: PRIVATE CAR | M86: 8706 | N86: 13.266713 | O86: 1155 | P86: Delhi | Q86: 443810 | R86: 0 | T86: Saurabh Dwivedi | U86: Mohit Mendiratta | V86: GGN/23-24/378 | W86: 3075 | X86: Rushiraj | AA86: TP Brok % need to modify | AC86: Modification | AD86: Jun'23
A87: Jun'25 | C87: 510000 | D87: CBRO DELHI | E87: OIC/25-26/1013 | F87: 510000/48/2023/1562 | G87: 3 | H87: Fractal Ink Design Studio Private Limited | I87: 44964 | J87: 45291 | K87: MIST-PRD-890 | L87: GROUP MEDICLAIM -TAILORMADE-RISK FLOATER | M87: 10080 | N87: 5 | O87: 504 | P87: Delhi | Q87: 430684 | R87: NE | T87: Amit Pandey | U87: Niladri Mangal Choudhury | V87: GGN/23-24/384 | W87: 3081 | X87: Rushiraj | AC87: NE | AD87: Jun'23
A88: Jun'25 | C88: 510000 | D88: CBRO DELHI | E88: OIC/25-26/1014 | F88: 510000/48/2023/1411 | G88: 8 | H88: HAYS BUSINESS SOLUTIONS PVT LTD | I88: 44927 | J88: 45291 | K88: MIST-PRD-890 | L88: GROUP MEDICLAIM -TAILORMADE-RISK FLOATER | M88: -92175 | N88: 7.5000054 | O88: -6913.13 | P88: Delhi | Q88: 421505 | R88: E2 | T88: Abhishek Sharma | U88: Ishita Sharma | V88: GGN/23-24/384 | W88: 3081 | X88: Rushiraj | AB88: Part | AC88: Updation done in Saiba | AD88: Jun'23
A89: Jun'25 | C89: 215600 | D89: DO 4 NEW DELHI | E89: OIC/25-26/1015 | F89: 215600/31/2024/258 | G89: 0 | H89: DELHIVERY LTD | I89: 45093 | J89: 45458 | K89: MOT-PRD-003 | L89: GCCV | M89: 78419 | N89: 7.9993369 | O89: 6273 | P89: Delhi | Q89: NE | R89: NE | T89: Saurabh Dwivedi | U89: Santosh Kumar Gupta | V89: GGN/23-24/379 | W89: 3076 | X89: Rushiraj | Z89: No | AC89: NE | AD89: Jun'23
A90: Jun'25 | C90: 212203 | D90: CBO 13 N-34 C.PLACE | E90: OIC/25-26/1016 | F90: 212203/31/2024/574 | G90: 0 | H90: ENERGY EFFICIENCY SERVICES LTD | I90: 45085 | J90: 45450 | K90: MOT-PRD-015 | L90: STANDALONE OWN DAMAGE(OD)-PRIVATE CAR | M90: 8914 | N90: 15.010096 | O90: 1338 | P90: Delhi | Q90: 443956 | R90: 0 | T90: Saurabh Dwivedi | U90: Mohit Mendiratta | V90: GGN/23-24/378 | W90: 3075 | X90: Rushiraj | AC90: Updation done in Saiba | AD90: Jun'23
A91: Jun'25 | C91: 510000 | D91: CBRO DELHI | E91: OIC/25-26/1017 | F91: 510000/48/2023/1563 | G91: 2 | H91: MILESTONE BRANDCOM PRIVATE LIMITED | I91: 44964 | J91: 45291 | K91: MIST-PRD-890 | L91: GROUP MEDICLAIM -TAILORMADE-RISK FLOATER | M91: -4270 | N91: 5 | O91: -213.5 | P91: Delhi | Q91: 430683 | R91: NE | T91: Amit Pandey | U91: Niladri Mangal Choudhury | V91: GGN/23-24/384 | W91: 3081 | X91: Rushiraj | AC91: NE | AD91: Jun'23
A92: Jun'25 | C92: 212203 | D92: CBO 13 N-34 C.PLACE | E92: OIC/25-26/1018 | F92: 212203/31/2024/597 | G92: 0 | H92: ENERGY EFFICIENCY SERVICES LIMITED | I92: 45088 | J92: 45453 | K92: MOT-PRD-001 | L92: PRIVATE CAR | M92: 18869 | N92: 13.747416 | O92: 2594 | P92: Delhi | Q92: 443823 | R92: 0 | T92: Saurabh Dwivedi | U92: Mohit Mendiratta | V92: GGN/23-24/378 | W92: 3075 | X92: Rushiraj | AC92: Modification | AD92: Jun'23
A93: Jun'25 | C93: 212203 | D93: CBO 13 N-34 C.PLACE | E93: OIC/25-26/1019 | F93: 212203/31/2024/765 | G93: 0 | H93: EXPORT CREDIT GUARANTEE CORPORATION | I93: 45111 | J93: 45476 | K93: MOT-PRD-015 | L93: STANDALONE OWN DAMAGE(OD)-PRIVATE CAR | M93: 8111 | N93: 14.991986 | O93: 1216 | P93: Delhi | Q93: NE | R93: NE | T93: Suspense | U93: Suspense | V93: GGN/23-24/378 | W93: 3075 | X93: Rushiraj | Z93: No | AC93: NE | AD93: Jun'23
A94: Jun'25 | C94: 212203 | D94: CBO 13 N-34 C.PLACE | E94: OIC/25-26/1020 | F94: 212203/31/2024/769 | G94: 0 | H94: EXPORT CREDIT GUARANTEE CORPORATION | I94: 45111 | J94: 45476 | K94: MOT-PRD-015 | L94: STANDALONE OWN DAMAGE(OD)-PRIVATE CAR | M94: 8111 | N94: 14.991986 | O94: 1216 | P94: Delhi | Q94: NE | R94: NE | T94: Suspense | U94: Suspense | V94: GGN/23-24/378 | W94: 3075 | X94: Rushiraj | Z94: No | AC94: NE | AD94: Jun'23
A95: Jun'25 | C95: 411700 | D95: DO 7 CHENNAI | E95: OIC/25-26/1021 | F95: 411700/48/2023/2420 | G95: 11 | H95: FINANCIAL SOFTWARE & SYSTEMS (P) LTD | I95: 44835 | J95: 45199 | K95: MIST-PRD-890 | L95: GROUP MEDICLAIM -TAILORMADE-RISK FLOATER | M95: -50998 | N95: 1.0000392 | O95: -510 | P95: Chennai | Q95: 407988 | R95: E8 | T95: Meenakshi Menon | U95: Sudha.S | V95: CHN/23-24/123 | W95: 3069 | X95: Rushiraj | AC95: Saiba Error | AD95: Jun'23
A96: Jun'25 | C96: 510000 | D96: CBRO DELHI | E96: OIC/25-26/1022 | F96: 510000/48/2023/1580 | G96: 2 | H96: DENTSU ADVERTISING AND MEDIA SERVICES INDIA PRIVATE LIMITED | I96: 44964 | J96: 45291 | K96: MIST-PRD-001 | L96: GPA - NAMED | M96: -560 | N96: 7.5 | O96: -42 | P96: Delhi | Q96: 429605 | R96: NE | T96: Amit Pandey | U96: Niladri Mangal Choudhury | V96: GGN/23-24/384 | W96: 3081 | X96: Rushiraj | AC96: NE | AD96: Jun'23
A97: Jun'25 | C97: 510000 | D97: CBRO DELHI | E97: OIC/25-26/1023 | F97: 510000/48/2023/1557 | G97: 2 | H97: SOKRATI TECHNOLOGIES PRIVATE LIMITED | I97: 44938 | J97: 45291 | K97: MIST-PRD-890 | L97: GROUP MEDICLAIM -TAILORMADE-RISK FLOATER | M97: -180304 | N97: 5 | O97: -9015.2 | P97: Delhi | Q97: 430690 | R97: NE | T97: Amit Pandey | U97: Niladri Mangal Choudhury | V97: GGN/23-24/384 | W97: 3081 | X97: Rushiraj | AC97: NE | AD97: Jun'23
A98: Jun'25 | C98: 540000 | D98: CBO BANGALORE | E98: OIC/25-26/1024 | F98: 421300/48/2023/1267 | G98: 3 | H98: FRESHALICIOUS SUPER BAZAAR PRIVATE LIMITED | I98: 44919 | J98: 45283 | K98: MIST-PRD-001 | L98: GPA - NAMED | M98: 241896 | N98: 7.4999173 | O98: 18142 | P98: Bangalore | Q98: NE | R98: NE | T98: Jaya Chitra.M | U98: Raghuram P S | V98: BLR/23-24/183 | W98: 3123 | X98: Rushiraj | AC98: NE | AD98: Jun'23
A99: Jun'25 | C99: 112400 | D99: MRO 1 Aviation Cell | E99: OIC/25-26/1025 | F99: 112400/43/2024/45 | G99: 0 | H99: JET SERVE AVIATION PRIVATE LIMITED | I99: 45082 | J99: 45447 | K99: AVI-PRD-011 | L99: HULL WAR RISK | M99: 7875 | N99: 9.9809524 | O99: 786 | P99: Delhi | Q99: 436324 | R99: 0 | T99: Vineet Khattar | U99: Varun Malik | V99: MUM/23-24/569 | W99: 3087 | X99: Rushiraj | AC99: Updation done in Saiba | AD99: Jun'23
A100: Jun'25 | C100: 540000 | D100: CBO BANGALORE | E100: OIC/25-26/1026 | F100: 540000/48/2024/40 | G100: 0 | H100: KERN-LIEBERS (INDIA) PRIVATE LIMITED | I100: 45110 | J100: 45475 | K100: MIST-PRD-052 | L100: MONEY INSURANCE | M100: 1188 | N100: 12.542088 | O100: 149 | P100: Bangalore | Q100: 441722 | R100: 0 | T100: Anusha Jaiswal | U100: Priya Pant | V100: BLR/23-24/183 | W100: 3123 | X100: Rushiraj | AC100: Updation done in Saiba | AD100: Jun'23
...

Sheet Sheet3
A1: Month | B1: (All) | D1: Row Labels | E1: Sum of Commission | L1: Remarks
D2: BLR/23-24/100 | E2: 1586835.8 | F2: =VLOOKUP(D2,'[1]Sales Register'!$E:$I,5,0) -> 1586835.8 | G2: =E2-F2 -> 0 | I2: Done | J2: =VLOOKUP(D2,Data!V:AD,9,0) -> #N/A
A3: Row Labels | B3: Sum of Commission | D3: BLR/23-24/101 | E3: 119553.1 | F3: =VLOOKUP(D3,'[1]Sales Register'!$E:$I,5,0) -> 119553.1 | G3: =E3-F3 -> 0 | I3: Done | J3: =VLOOKUP(D3,Data!V:AD,9,0) -> #N/A
A4: BLR/23-24/100 | B4: 1586835.8 | D4: BLR/23-24/102 | E4: 481686.51 | F4: =VLOOKUP(D4,'[1]Sales Register'!$E:$I,5,0) -> 481686.51 | G4: =E4-F4 -> 0 | I4: Done | J4: =VLOOKUP(D4,Data!V:AD,9,0) -> #N/A
A5: BLR/23-24/101 | B5: 119553.1 | D5: BLR/23-24/103 | E5: 831 | F5: =VLOOKUP(D5,'[1]Sales Register'!$E:$I,5,0) -> 831 | G5: =E5-F5 -> 0 | I5: Done | J5: =VLOOKUP(D5,Data!V:AD,9,0) -> #N/A
A6: BLR/23-24/102 | B6: 481686.51 | D6: BLR/23-24/104 | E6: 2362 | F6: =VLOOKUP(D6,'[1]Sales Register'!$E:$I,5,0) -> 2362 | G6: =E6-F6 -> 0 | I6: Done | J6: =VLOOKUP(D6,Data!V:AD,9,0) -> #N/A
A7: BLR/23-24/103 | B7: 831 | D7: BLR/23-24/172 | E7: 221395.68 | F7: =VLOOKUP(D7,'[1]Sales Register'!$E:$I,5,0) -> 221395.68 | G7: =E7-F7 -> 0 | I7: Done | J7: =VLOOKUP(D7,Data!V:AD,9,0) -> Jun'23
A8: BLR/23-24/104 | B8: 2362 | D8: BLR/23-24/173 | E8: 132287 | F8: =VLOOKUP(D8,'[1]Sales Register'!$E:$I,5,0) -> 132287 | G8: =E8-F8 -> 0 | I8: Done | J8: =VLOOKUP(D8,Data!V:AD,9,0) -> Jun'23
A9: BLR/23-24/172 | B9: 221395.68 | D9: BLR/23-24/174 | E9: 1357 | F9: =VLOOKUP(D9,'[1]Sales Register'!$E:$I,5,0) -> 1357 | G9: =E9-F9 -> 0 | I9: Done | J9: =VLOOKUP(D9,Data!V:AD,9,0) -> Jun'23
A10: BLR/23-24/173 | B10: 132287 | D10: BLR/23-24/183 | E10: 265064.66 | F10: =VLOOKUP(D10,'[1]Sales Register'!$E:$I,5,0) -> 265064.66 | G10: =E10-F10 -> 0 | I10: Done | J10: =VLOOKUP(D10,Data!V:AD,9,0) -> Jun'23
A11: BLR/23-24/174 | B11: 1357 | D11: BLR/23-24/204 | E11: 606019.38 | F11: =VLOOKUP(D11,'[1]Sales Register'!$E:$I,5,0) -> 606019.38 | G11: =E11-F11 -> 0 | I11: Done | J11: =VLOOKUP(D11,Data!V:AD,9,0) -> #N/A
A12: BLR/23-24/183 | B12: 265064.66 | D12: BLR/23-24/205 | E12: 765269 | F12: =VLOOKUP(D12,'[1]Sales Register'!$E:$I,5,0) -> 765269 | G12: =E12-F12 -> 0 | I12: Done | J12: =VLOOKUP(D12,Data!V:AD,9,0) -> #N/A
A13: BLR/23-24/204 | B13: 606019.38 | D13: BLR/23-24/206 | E13: 11881.43 | F13: =VLOOKUP(D13,'[1]Sales Register'!$E:$I,5,0) -> 11881.43 | G13: =E13-F13 -> 0 | I13: Done | J13: =VLOOKUP(D13,Data!V:AD,9,0) -> #N/A
A14: BLR/23-24/205 | B14: 765269 | D14: BLR/23-24/62 | E14: 3186.56 | F14: =VLOOKUP(D14,'[1]Sales Register'!$E:$I,5,0) -> 3186.56 | G14: =E14-F14 -> 0 | I14: Done | J14: =VLOOKUP(D14,Data!V:AD,9,0) -> #N/A
A15: BLR/23-24/206 | B15: 11881.43 | D15: BLR/23-24/63 | E15: 729671 | F15: =VLOOKUP(D15,'[1]Sales Register'!$E:$I,5,0) -> 729671 | G15: =E15-F15 -> 0 | I15: Done | J15: =VLOOKUP(D15,Data!V:AD,9,0) -> #N/A
... A17: BLR/23-24/63 | B17: 729671 | D17: BLR/23-24/65 | E17: 418800 | F17: =VLOOKUP(D17,'[1]Sales Register'!$E:$I,5,0) -> 418800 | G17: =E17-F17 -> 0 | I17: Done | J17: =VLOOKUP(D17,Data!V:AD,9,0) -> #N/A
A18: BLR/23-24/64 | B18: 374752.63 | D18: BLR/C/23-24/04 | E18: -61632 | F18: =VLOOKUP(D18,'[1]Sales Register'!$E:$I,5,0) -> #N/A | G18: =E18-F18 -> #N/A | H18: =VLOOKUP(D18,'[1]Credit Note Register'!$E:$I,5,0) -> 61632 | I18: Done | J18: =VLOOKUP(D18,Data!V:AD,9,0) -> #N/A
A19: BLR/23-24/65 | B19: 418800 | D19: BLR/C/23-24/07 | E19: -34888 | F19: =VLOOKUP(D19,'[1]Sales Register'!$E:$I,5,0) -> #N/A | G19: =E19-F19 -> #N/A | H19: =VLOOKUP(D19,'[1]Credit Note Register'!$E:$I,5,0) -> 34888 | I19: Done | J19: =VLOOKUP(D19,Data!V:AD,9,0) -> Jun'23
A20: BLR/C/23-24/04 | B20: -61632 | D20: BLR/C/23-24/13 | E20: 1691.9 | F20: =VLOOKUP(D20,'[1]Sales Register'!$E:$I,5,0) -> #N/A | G20: =E20-F20 -> #N/A | H20: =VLOOKUP(D20,'[1]Credit Note Register'!$E:$I,5,0) -> 368.63 | I20: Done | J20: =VLOOKUP(D20,Data!V:AD,9,0) -> #N/A
A21: BLR/C/23-24/07 | B21: -34888 | D21: CHN/23-24/122 | E21: 76800 | F21: =VLOOKUP(D21,'[1]Sales Register'!$E:$I,5,0) -> 76800 | G21: =E21-F21 -> 0 | I21: Done | J21: =VLOOKUP(D21,Data!V:AD,9,0) -> Jun'23
A22: BLR/C/23-24/13 | B22: 1691.9 | D22: CHN/23-24/123 | E22: 34.99 | F22: =VLOOKUP(D22,'[1]Sales Register'!$E:$I,5,0) -> 34.99 | G22: =E22-F22 -> 0 | I22: Done | J22: =VLOOKUP(D22,Data!V:AD,9,0) -> Jun'23
A23: CHN/23-24/122 | B23: 76800 | D23: CHN/23-24/124 | E23: 341.7 | F23: =VLOOKUP(D23,'[1]Sales Register'!$E:$I,5,0) -> 341.7 | G23: =E23-F23 -> 0 | I23: Done | J23: =VLOOKUP(D23,Data!V:AD,9,0) -> Jun'23
A24: CHN/23-24/123 | B24: 34.99 | D24: CHN/23-24/125 | E24: 3855 | F24: =VLOOKUP(D24,'[1]Sales Register'!$E:$I,5,0) -> 3855 | G24: =E24-F24 -> 0 | I24: Done | J24: =VLOOKUP(D24,Data!V:AD,9,0) -> Jun'23
A25: CHN/23-24/124 | B25: 341.7 | D25: CHN/23-24/126 | E25: 3 | F25: =VLOOKUP(D25,'[1]Sales Register'!$E:$I,5,0) -> 3 | G25: =E25-F25 -> 0 | I25: Done | J25: =VLOOKUP(D25,Data!V:AD,9,0) -> Jun'23
A26: CHN/23-24/125 | B26: 3855 | D26: CHN/23-24/127 | E26: 17564 | F26: =VLOOKUP(D26,'[1]Sales Register'!$E:$I,5,0) -> 17564 | G26: =E26-F26 -> 0 | I26: Done | J26: =VLOOKUP(D26,Data!V:AD,9,0) -> Jun'23
A27: CHN/23-24/126 | B27: 3 | D27: CHN/23-24/148 | E27: 11318.37 | F27: =VLOOKUP(D27,'[1]Sales Register'!$E:$I,5,0) -> 4.72 | G27: =VLOOKUP(E27,'[1]Sales Register'!$E:$I,5,0) -> #N/A | H27: =VLOOKUP(D27,'[1]Credit Note Register'!$E:$I,5,0) -> #N/A | I27: Done | J27: =VLOOKUP(D27,Data!V:AD,9,0) -> #N/A
A28: CHN/23-24/127 | B28: 17564 | D28: CHN/23-24/44 | E28: 247 | F28: =VLOOKUP(D28,'[1]Sales Register'!$E:$I,5,0) -> 247 | G28: =E28-F28 -> 0 | I28: Done | J28: =VLOOKUP(D28,Data!V:AD,9,0) -> #N/A
A29: CHN/23-24/148 | B29: 11318.37 | D29: CHN/23-24/45 | E29: 1860.53 | F29: =VLOOKUP(D29,'[1]Sales Register'!$E:$I,5,0) -> 1860.53 | G29: =E29-F29 -> 0 | I29: Done | J29: =VLOOKUP(D29,Data!V:AD,9,0) -> #N/A
A30: CHN/23-24/44 | B30: 247 | D30: CHN/23-24/46 | E30: 1250.39 | F30: =VLOOKUP(D30,'[1]Sales Register'!$E:$I,5,0) -> 1250.39 | G30: =E30-F30 -> 0 | I30: Done | J30: =VLOOKUP(D30,Data!V:AD,9,0) -> #N/A
A31: CHN/23-24/45 | B31: 1860.53 | D31: CHN/23-24/47 | E31: 8217 | F31: =VLOOKUP(D31,'[1]Sales Register'!$E:$I,5,0) -> 8217 | G31: =E31-F31 -> 0 | I31: Done | J31: =VLOOKUP(D31,Data!V:AD,9,0) -> #N/A
A32: CHN/23-24/46 | B32: 1250.39 | D32: CHN/23-24/48 | E32: 923 | F32: =VLOOKUP(D32,'[1]Sales Register'!$E:$I,5,0) -> 923 | G32: =E32-F32 -> 0 | I32: Done | J32: =VLOOKUP(D32,Data!V:AD,9,0) -> #N/A
A33: CHN/23-24/47 | B33: 8217 | D33: CHN/23-24/49 | E33: 48628 | F33: =VLOOKUP(D33,'[1]Sales Register'!$E:$I,5,0) -> 48628 | G33: =E33-F33 -> 0 | I33: Done | J33: =VLOOKUP(D33,Data!V:AD,9,0) -> #N/A
A34: CHN/23-24/48 | B34: 923 | D34: CHN/23-24/63 | E34: 2002.88 | F34: =VLOOKUP(D34,'[1]Sales Register'!$E:$I,5,0) -> 2002.88 | G34: =E34-F34 -> 0 | I34: Done | J34: =VLOOKUP(D34,Data!V:AD,9,0) -> #N/A
A35: CHN/23-24/49 | B35: 48628 | D35: CHN/23-24/64 | E35: 937.6 | F35: =VLOOKUP(D35,'[1]Sales Register'!$E:$I,5,0) -> 937.6 | G35: =E35-F35 -> 0 | I35: Done | J35: =VLOOKUP(D35,Data!V:AD,9,0) -> #N/A
A36: CHN/23-24/63 | B36: 2002.88 | D36: CHN/23-24/65 | E36: 772.35 | F36: =VLOOKUP(D36,'[1]Sales Register'!$E:$I,5,0) -> 772.35 | G36: =E36-F36 -> 0 | I36: Done | J36: =VLOOKUP(D36,Data!V:AD,9,0) -> #N/A
A37: CHN/23-24/64 | B37: 937.6 | D37: CHN/23-24/66 | E37: 1270 | F37: =VLOOKUP(D37,'[1]Sales Register'!$E:$I,5,0) -> 1270 | G37: =E37-F37 -> 0 | I37: Done | J37: =VLOOKUP(D37,Data!V:AD,9,0) -> #N/A
A38: CHN/23-24/65 | B38: 772.35 | D38: CHN/23-24/67 | E38: 201712.91 | F38: =VLOOKUP(D38,'[1]Sales Register'!$E:$I,5,0) -> 201712.91 | G38: =E38-F38 -> 0 | I38: Done | J38: =VLOOKUP(D38,Data!V:AD,9,0) -> #N/A
A39: CHN/23-24/66 | B39: 1270 | D39: CHN/C/23-24/11 | E39: -326.78 | F39: =VLOOKUP(D39,'[1]Sales Register'!$E:$I,5,0) -> #N/A | G39: =E39-F39 -> #N/A | H39: =VLOOKUP(D39,'[1]Credit Note Register'!$E:$I,5,0) -> 326.78 | I39: Done | J39: =VLOOKUP(D39,Data!V:AD,9,0) -> #N/A
A40: CHN/23-24/67 | B40: 201712.91 | D40: CHN/C/23-24/14 | E40: -1128 | F40: =VLOOKUP(D40,'[1]Sales Register'!$E:$I,5,0) -> #N/A | G40: =E40-F40 -> #N/A | H40: =VLOOKUP(D40,'[1]Credit Note Register'!$E:$I,5,0) -> 1128 | I40: Done | J40: =VLOOKUP(D40,Data!V:AD,9,0) -> #N/A
A41: CHN/C/23-24/11 | B41: -326.78 | D41: CHN/C/23-24/24 | E41: -7.65 | F41: =VLOOKUP(D41,'[1]Sales Register'!$E:$I,5,0) -> #N/A | G41: =E41-F41 -> #N/A | H41: =VLOOKUP(D41,'[1]Credit Note Register'!$E:$I,5,0) -> 7.65 | I41: Done | J41: =VLOOKUP(D41,Data!V:AD,9,0) -> Jun'23
A42: CHN/C/23-24/14 | B42: -1128 | D42: CHN/C/23-24/30 | E42: -2351.06 | F42: =VLOOKUP(D42,'[1]Sales Register'!$E:$I,5,0) -> #N/A | G42: =E42-F42 -> #N/A | H42: =VLOOKUP(D42,'[1]Credit Note Register'!$E:$I,5,0) -> 900.06 | I42: Done | J42: =VLOOKUP(D42,Data!V:AD,9,0) -> #N/A
A43: CHN/C/23-24/24 | B43: -7.65 | D43: CHN/C/23-24/31 | E43: -16 | F43: =VLOOKUP(D43,'[1]Sales Register'!$E:$I,5,0) -> #N/A | G43: =E43-F43 -> #N/A | H43: =VLOOKUP(D43,'[1]Credit Note Register'!$E:$I,5,0) -> 16 | I43: Done | J43: =VLOOKUP(D43,Data!V:AD,9,0) -> #N/A
A44: CHN/C/23-24/30 | B44: -2351.06 | D44: GGN/23-24/128 | E44: 459 | F44: =VLOOKUP(D44,'[1]Sales Register'!$E:$I,5,0) -> 459 | G44: =E44-F44 -> 0 | I44: Done | J44: =VLOOKUP(D44,Data!V:AD,9,0) -> #N/A
A45: CHN/C/23-24/31 | B45: -16 | D45: GGN/23-24/129 | E45: 28679854 | F45: =VLOOKUP(D45,'[1]Sales Register'!$E:$I,5,0) -> 28679854 | G45: =E45-F45 -> 0 | I45: Done | J45: =VLOOKUP(D45,Data!V:AD,9,0) -> #N/A
A46: GGN/23-24/128 | B46: 459 | D46: GGN/23-24/130 | E46: 23.79 | F46: =VLOOKUP(D46,'[1]Sales Register'!$E:$I,5,0) -> 23.79 | G46: =E46-F46 -> -3.5527137e-14 | H46: =VLOOKUP(D46,'[1]Credit Note Register'!$E:$I,5,0) -> #N/A | I46: Done | J46: =VLOOKUP(D46,Data!V:AD,9,0) -> #N/A
A47: GGN/23-24/129 | B47: 28679854 | D47: GGN/23-24/131 | E47: 5772 | F47: =VLOOKUP(D47,'[1]Sales Register'!$E:$I,5,0) -> 5772 | G47: =E47-F47 -> 0 | I47: Done | J47: =VLOOKUP(D47,Data!V:AD,9,0) -> #N/A
A48: GGN/23-24/130 | B48: 23.79 | D48: GGN/23-24/132 | E48: 2551 | F48: =VLOOKUP(D48,'[1]Sales Register'!$E:$I,5,0) -> 2551 | G48: =E48-F48 -> 0 | I48: Done | J48: =VLOOKUP(D48,Data!V:AD,9,0) -> #N/A
A49: GGN/23-24/131 | B49: 5772 | D49: GGN/23-24/133 | E49: 55998 | F49: =VLOOKUP(D49,'[1]Sales Register'!$E:$I,5,0) -> 55998 | G49: =E49-F49 -> 0 | I49: Done | J49: =VLOOKUP(D49,Data!V:AD,9,0) -> #N/A
A50: GGN/23-24/132 | B50: 2551 | D50: GGN/23-24/134 | E50: 25312 | F50: =VLOOKUP(D50,'[1]Sales Register'!$E:$I,5,0) -> 25312 | G50: =E50-F50 -> 0 | I50: Done | J50: =VLOOKUP(D50,Data!V:AD,9,0) -> #N/A
A51: GGN/23-24/133 | B51: 55998 | D51: GGN/23-24/135 | E51: 14853 | F51: =VLOOKUP(D51,'[1]Sales Register'!$E:$I,5,0) -> 14853 | G51: =E51-F51 -> 0 | I51: Done | J51: =VLOOKUP(D51,Data!V:AD,9,0) -> #N/A
A52: GGN/23-24/134 | B52: 25312 | D52: GGN/23-24/136 | E52: 61092 | F52: =VLOOKUP(D52,'[1]Sales Register'!$E:$I,5,0) -> 61092 | G52: =E52-F52 -> 0 | I52: Done | J52: =VLOOKUP(D52,Data!V:AD,9,0) -> #N/A
A53: GGN/23-24/135 | B53: 14853 | D53: GGN/23-24/137 | E53: 681373.11 | F53: =VLOOKUP(D53,'[1]Sales Register'!$E:$I,5,0) -> 681373.11 | G53: =E53-F53 -> 0 | I53: Done | J53: =VLOOKUP(D53,Data!V:AD,9,0) -> #N/A
A54: GGN/23-24/136 | B54: 61092 | D54: GGN/23-24/172 | E54: 21847282 | F54: =VLOOKUP(D54,'[1]Sales Register'!$E:$I,5,0) -> 3277092.3 | G54: =E54-F54 -> 18570190 | H54: =VLOOKUP(D54,'[1]Credit Note Register'!$E:$I,5,0) -> #N/A | I54: Done | J54: =VLOOKUP(D54,Data!V:AD,9,0) -> #N/A | K54: tally with 15% share
A55: GGN/23-24/137 | B55: 681373.11 | D55: GGN/23-24/216 | E55: 44438 | F55: =VLOOKUP(D55,'[1]Sales Register'!$E:$I,5,0) -> 44438 | G55: =E55-F55 -> 0 | I55: Done | J55: =VLOOKUP(D55,Data!V:AD,9,0) -> #N/A
A56: GGN/23-24/172 | B56: 3277092.3 | D56: GGN/23-24/217 | E56: 416152 | F56: =VLOOKUP(D56,'[1]Sales Register'!$E:$I,5,0) -> 416152 | G56: =E56-F56 -> 0 | I56: Done | J56: =VLOOKUP(D56,Data!V:AD,9,0) -> #N/A
A57: GGN/23-24/216 | B57: 44438 | D57: GGN/23-24/218 | E57: 1421429 | F57: =VLOOKUP(D57,'[1]Sales Register'!$E:$I,5,0) -> 1054981.7 | G57: =E57-F57 -> 366447.3 | H57: =VLOOKUP(D57,'[1]Credit Note Register'!$E:$I,5,0) -> #N/A | I57: Done | J57: =VLOOKUP(D57,Data!V:AD,9,0) -> #N/A | L57: Revised statement _not woking( invoice cancelled)
A58: GGN/23-24/217 | B58: 416152 | D58: GGN/23-24/219 | E58: 1403 | F58: =VLOOKUP(D58,'[1]Sales Register'!$E:$I,5,0) -> 1403 | G58: =E58-F58 -> 0 | I58: Done | J58: =VLOOKUP(D58,Data!V:AD,9,0) -> #N/A
A59: GGN/23-24/218 | B59: 1421429 | D59: GGN/23-24/220 | E59: 1254 | F59: =VLOOKUP(D59,'[1]Sales Register'!$E:$I,5,0) -> 1254 | G59: =E59-F59 -> 0 | I59: Done | J59: =VLOOKUP(D59,Data!V:AD,9,0) -> #N/A
A60: GGN/23-24/219 | B60: 1403 | D60: GGN/23-24/221 | E60: 89709 | F60: =VLOOKUP(D60,'[1]Sales Register'!$E:$I,5,0) -> 89709 | G60: =E60-F60 -> 0 | I60: Done | J60: =VLOOKUP(D60,Data!V:AD,9,0) -> #N/A
A61: GGN/23-24/220 | B61: 1254 | D61: GGN/23-24/222 | E61: 33011 | F61: =VLOOKUP(D61,'[1]Sales Register'!$E:$I,5,0) -> 33011 | G61: =E61-F61 -> 0 | I61: Done | J61: =VLOOKUP(D61,Data!V:AD,9,0) -> #N/A
A62: GGN/23-24/221 | B62: 89709 | D62: GGN/23-24/223 | E62: 2963805 | F62: =VLOOKUP(D62,'[1]Sales Register'!$E:$I,5,0) -> 2963805 | G62: =E62-F62 -> 0 | I62: Done | J62: =VLOOKUP(D62,Data!V:AD,9,0) -> #N/A
A63: GGN/23-24/222 | B63: 33011 | D63: GGN/23-24/224 | E63: 6779.23 | F63: =VLOOKUP(D63,'[1]Sales Register'!$E:$I,5,0) -> 6779.23 | G63: =E63-F63 -> 0 | I63: Done | J63: =VLOOKUP(D63,Data!V:AD,9,0) -> #N/A
A64: GGN/23-24/223 | B64: 2963805 | D64: GGN/23-24/225 | E64: 104741 | F64: =VLOOKUP(D64,'[1]Sales Register'!$E:$I,5,0) -> 104741 | G64: =E64-F64 -> 0 | I64: Done | J64: =VLOOKUP(D64,Data!V:AD,9,0) -> #N/A
A65: GGN/23-24/224 | B65: 6779.23 | D65: GGN/23-24/226 | E65: 19821 | F65: =VLOOKUP(D65,'[1]Sales Register'!$E:$I,5,0) -> 19821 | G65: =E65-F65 -> 0 | I65: Done | J65: =VLOOKUP(D65,Data!V:AD,9,0) -> #N/A
A66: GGN/23-24/225 | B66: 104741 | D66: GGN/23-24/227 | E66: 7249 | F66: =VLOOKUP(D66,'[1]Sales Register'!$E:$I,5,0) -> 7249 | G66: =E66-F66 -> 0 | I66: Done | J66: =VLOOKUP(D66,Data!V:AD,9,0) -> #N/A
A67: GGN/23-24/226 | B67: 19821 | D67: GGN/23-24/377 | E67: 51713 | F67: =VLOOKUP(D67,'[1]Sales Register'!$E:$I,5,0) -> 51713 | G67: =E67-F67 -> 0 | I67: Done | J67: =VLOOKUP(D67,Data!V:AD,9,0) -> Jun'23
A68: GGN/23-24/227 | B68: 7249 | D68: GGN/23-24/378 | E68: 171937.2 | F68: =VLOOKUP(D68,'[1]Sales Register'!$E:$I,5,0) -> 171937.2 | G68: =E68-F68 -> 0 | I68: Done | J68: =VLOOKUP(D68,Data!V:AD,9,0) -> Jun'23
A69: GGN/23-24/377 | B69: 51713 | D69: GGN/23-24/379 | E69: 143631.28 | F69: =VLOOKUP(D69,'[1]Sales Register'!$E:$I,5,0) -> 139964 | G69: =E69-F69 -> 3667.28 | H69: =VLOOKUP(D69,'[1]Credit Note Register'!$E:$I,5,0) -> #N/A | I69: Done | J69: =VLOOKUP(D69,Data!V:AD,9,0) -> Jun'23
A70: GGN/23-24/378 | B70: 171937.2 | D70: GGN/23-24/381 | E70: 59399 | F70: =VLOOKUP(D70,'[1]Sales Register'!$E:$I,5,0) -> 59399 | G70: =E70-F70 -> 0 | I70: Done | J70: =VLOOKUP(D70,Data!V:AD,9,0) -> Jun'23
A71: GGN/23-24/379 | B71: 143631.28 | D71: GGN/23-24/382 | E71: 21799 | F71: =VLOOKUP(D71,'[1]Sales Register'!$E:$I,5,0) -> 21799 | G71: =E71-F71 -> 0 | I71: Done | J71: =VLOOKUP(D71,Data!V:AD,9,0) -> Jun'23
A72: GGN/23-24/381 | B72: 59399 | D72: GGN/23-24/383 | E72: 59090 | F72: =VLOOKUP(D72,'[1]Sales Register'!$E:$I,5,0) -> 59090 | G72: =E72-F72 -> 0 | I72: Done | J72: =VLOOKUP(D72,Data!V:AD,9,0) -> Jun'23
A73: GGN/23-24/382 | B73: 21799 | D73: GGN/23-24/384 | E73: 14724953 | F73: =VLOOKUP(D73,'[1]Sales Register'!$E:$I,5,0) -> 14724953 | G73: =E73-F73 -> 0 | I73: Done | J73: =VLOOKUP(D73,Data!V:AD,9,0) -> Jun'23
A74: GGN/23-24/383 | B74: 59090 | D74: GGN/23-24/431 | E74: 319016 | F74: =VLOOKUP(D74,'[1]Sales Register'!$E:$I,5,0) -> 390812 | G74: =E74-F74 -> -71796 | H74: =VLOOKUP(D74,'[1]Credit Note Register'!$E:$I,5,0) -> #N/A | I74: Done | J74: =VLOOKUP(D74,Data!V:AD,9,0) -> #N/A
A75: GGN/23-24/384 | B75: 14724953 | D75: GGN/23-24/432 | E75: 10041.75 | F75: =VLOOKUP(D75,'[1]Sales Register'!$E:$I,5,0) -> 296574.75 | G75: =E75-F75 -> -286533 | H75: =VLOOKUP(D75,'[1]Credit Note Register'!$E:$I,5,0) -> #N/A | I75: Done | J75: =VLOOKUP(D75,Data!V:AD,9,0) -> #N/A
A76: GGN/23-24/431 | B76: 319016 | D76: GGN/23-24/433 | E76: 2811.32 | F76: =VLOOKUP(D76,'[1]Sales Register'!$E:$I,5,0) -> 2811.32 | G76: =E76-F76 -> 0 | I76: Done | J76: =VLOOKUP(D76,Data!V:AD,9,0) -> #N/A
A77: GGN/23-24/432 | B77: 10041.75 | D77: GGN/23-24/434 | E77: 26261 | F77: =VLOOKUP(D77,'[1]Sales Register'!$E:$I,5,0) -> 57143 | G77: =E77-F77 -> -30882 | H77: =VLOOKUP(D77,'[1]Credit Note Register'!$E:$I,5,0) -> #N/A | I77: Done | J77: =VLOOKUP(D77,Data!V:AD,9,0) -> #N/A
A78: GGN/23-24/433 | B78: 2811.32 | D78: GGN/23-24/436 | E78: 57621 | F78: =VLOOKUP(D78,'[1]Sales Register'!$E:$I,5,0) -> 73902 | G78: =E78-F78 -> -16281 | H78: =VLOOKUP(D78,'[1]Credit Note Register'!$E:$I,5,0) -> #N/A | I78: Done | J78: =VLOOKUP(D78,Data!V:AD,9,0) -> #N/A
A79: GGN/23-24/434 | B79: 26261 | D79: GGN/C/23-24/57 | E79: -115506.44 | F79: =VLOOKUP(D79,'[1]Sales Register'!$E:$I,5,0) -> #N/A | G79: =E79-F79 -> #N/A | H79: =VLOOKUP(D79,'[1]Credit Note Register'!$E:$I,5,0) -> 63376.32 | I79: Done | J79: =VLOOKUP(D79,Data!V:AD,9,0) -> #N/A
A80: GGN/23-24/436 | B80: 57621 | D80: HYD/23-24/39 | E80: 1553900 | F80: =VLOOKUP(D80,'[1]Sales Register'!$E:$I,5,0) -> 1553900 | G80: =E80-F80 -> 0 | I80: Done | J80: =VLOOKUP(D80,Data!V:AD,9,0) -> #N/A
A81: GGN/C/23-24/57 | B81: -115506.44 | D81: HYD/23-24/40 | E81: 347500 | F81: =VLOOKUP(D81,'[1]Sales Register'!$E:$I,5,0) -> 347500 | G81: =E81-F81 -> 0 | I81: Done | J81: =VLOOKUP(D81,Data!V:AD,9,0) -> #N/A
A82: HYD/23-24/39 | B82: 1553900 | D82: HYD/23-24/73 | E82: 106183.78 | F82: =VLOOKUP(D82,'[1]Sales Register'!$E:$I,5,0) -> 106183.78 | G82: =E82-F82 -> 0 | I82: Done | J82: =VLOOKUP(D82,Data!V:AD,9,0) -> Jun'23
A83: HYD/23-24/40 | B83: 347500 | D83: HYD/23-24/84 | E83: 90543.71 | F83: =VLOOKUP(D83,'[1]Sales Register'!$E:$I,5,0) -> 234721.71 | G83: =E83-F83 -> -144178 | H83: =VLOOKUP(D83,'[1]Credit Note Register'!$E:$I,5,0) -> #N/A | I83: Done | J83: =VLOOKUP(D83,Data!V:AD,9,0) -> #N/A
A84: HYD/23-24/73 | B84: 106183.78 | D84: HYD/C/23-24/06 | E84: -115859.49 | F84: =VLOOKUP(D84,'[1]Sales Register'!$E:$I,5,0) -> #N/A | G84: =E84-F84 -> #N/A | H84: =VLOOKUP(D84,'[1]Credit Note Register'!$E:$I,5,0) -> 115859.49 | I84: Done | J84: =VLOOKUP(D84,Data!V:AD,9,0) -> #N/A
A85: HYD/23-24/84 | B85: 90543.71 | D85: Invoice in process | E85: 1861 | F85: =VLOOKUP(D85,'[1]Sales Register'!$E:$I,5,0) -> #N/A | G85: =E85-F85 -> #N/A | H85: =VLOOKUP(D85,'[1]Credit Note Register'!$E:$I,5,0) -> #N/A | J85: =VLOOKUP(D85,Data!V:AD,9,0) -> Jun'23
A86: HYD/C/23-24/06 | B86: -115859.49 | D86: Invoice not raise, 0 commission | E86: 0 | F86: =VLOOKUP(D86,'[1]Sales Register'!$E:$I,5,0) -> #N/A | G86: =E86-F86 -> #N/A | H86: =VLOOKUP(D86,'[1]Credit Note Register'!$E:$I,5,0) -> #N/A | J86: =VLOOKUP(D86,Data!V:AD,9,0) -> #N/A
A87: Invoice in process | B87: 1861 | D87: LUD/23-24/16 | E87: 6333 | F87: =VLOOKUP(D87,'[1]Sales Register'!$E:$I,5,0) -> 6333 | G87: =E87-F87 -> 0 | I87: Done | J87: =VLOOKUP(D87,Data!V:AD,9,0) -> #N/A
A88: Invoice not raise, 0 commission | B88: 0 | D88: LUD/23-24/17 | E88: 2371 | F88: =VLOOKUP(D88,'[1]Sales Register'!$E:$I,5,0) -> 2371 | G88: =E88-F88 -> 0 | I88: Done | J88: =VLOOKUP(D88,Data!V:AD,9,0) -> #N/A
A89: LUD/23-24/16 | B89: 6333 | D89: LUD/23-24/18 | E89: 32819 | F89: =VLOOKUP(D89,'[1]Sales Register'!$E:$I,5,0) -> 32819 | G89: =E89-F89 -> 0 | I89: Done | J89: =VLOOKUP(D89,Data!V:AD,9,0) -> #N/A
A90: LUD/23-24/17 | B90: 2371 | D90: LUD/23-24/28 | E90: 24920 | F90: =VLOOKUP(D90,'[1]Sales Register'!$E:$I,5,0) -> 24920 | G90: =E90-F90 -> 0 | I90: Done | J90: =VLOOKUP(D90,Data!V:AD,9,0) -> #N/A
A91: LUD/23-24/18 | B91: 32819 | D91: LUD/23-24/29 | E91: 89687.2 | F91: =VLOOKUP(D91,'[1]Sales Register'!$E:$I,5,0) -> 89687.2 | G91: =E91-F91 -> 0 | I91: Done | J91: =VLOOKUP(D91,Data!V:AD,9,0) -> #N/A
A92: LUD/23-24/28 | B92: 24920 | D92: LUD/23-24/30 | E92: 4089 | F92: =VLOOKUP(D92,'[1]Sales Register'!$E:$I,5,0) -> 4089 | G92: =E92-F92 -> 0 | I92: Done | J92: =VLOOKUP(D92,Data!V:AD,9,0) -> #N/A
A93: LUD/23-24/29 | B93: 89687.2 | D93: LUD/23-24/46 | E93: 22097 | F93: =VLOOKUP(D93,'[1]Sales Register'!$E:$I,5,0) -> 22097 | G93: =E93-F93 -> 0 | I93: Done | J93: =VLOOKUP(D93,Data!V:AD,9,0) -> Jun'23
A94: LUD/23-24/30 | B94: 4089 | D94: LUD/23-24/47 | E94: 3318.12 | F94: =VLOOKUP(D94,'[1]Sales Register'!$E:$I,5,0) -> 3318.12 | G94: =E94-F94 -> 0 | I94: Done | J94: =VLOOKUP(D94,Data!V:AD,9,0) -> Jun'23
A95: LUD/23-24/46 | B95: 22097 | D95: LUD/C/23-24/01 | E95: -14773.5 | F95: =VLOOKUP(D95,'[1]Sales Register'!$E:$I,5,0) -> #N/A | G95: =E95-F95 -> #N/A | H95: =VLOOKUP(D95,'[1]Credit Note Register'!$E:$I,5,0) -> 14773.5 | I95: Done | J95: =VLOOKUP(D95,Data!V:AD,9,0) -> #N/A
A96: LUD/23-24/47 | B96: 3318.12 | D96: MUM/23-24/179 | E96: 7263 | F96: =VLOOKUP(D96,'[1]Sales Register'!$E:$I,5,0) -> 7263 | G96: =E96-F96 -> 0 | I96: Done | J96: =VLOOKUP(D96,Data!V:AD,9,0) -> #N/A
A97: LUD/C/23-24/01 | B97: -14773.5 | D97: MUM/23-24/180 | E97: 24396.5 | F97: =VLOOKUP(D97,'[1]Sales Register'!$E:$I,5,0) -> 24396.5 | G97: =E97-F97 -> 0 | I97: Done | J97: =VLOOKUP(D97,Data!V:AD,9,0) -> #N/A
A98: MUM/23-24/179 | B98: 7263 | D98: MUM/23-24/181 | E98: 2877 | F98: =VLOOKUP(D98,'[1]Sales Register'!$E:$I,5,0) -> 2877 | G98: =E98-F98 -> 0 | I98: Done | J98: =VLOOKUP(D98,Data!V:AD,9,0) -> #N/A
A99: MUM/23-24/180 | B99: 24396.5 | D99: MUM/23-24/182 | E99: 1823.32 | F99: =VLOOKUP(D99,'[1]Sales Register'!$E:$I,5,0) -> 1823.32 | G99: =E99-F99 -> 0 | I99: Done | J99: =VLOOKUP(D99,Data!V:AD,9,0) -> #N/A
A100: MUM/23-24/181 | B100: 2877 | D100: MUM/23-24/183 | E100: 348750 | F100: =VLOOKUP(D100,'[1]Sales Register'!$E:$I,5,0) -> 348750 | G100: =E100-F100 -> 0 | I100: Done | J100: =VLOOKUP(D100,Data!V:AD,9,0) -> #N/A
A101: MUM/23-24/182 | B101: 1823.32 | D101: MUM/23-24/184 | E101: 59 | F101: =VLOOKUP(D101,'[1]Sales Register'!$E:$I,5,0) -> 59 | G101: =E101-F101 -> 0 | I101: Done | J101: =VLOOKUP(D101,Data!V:AD,9,0) -> #N/A
...
